Workbook

Sheet Target List
A1: Tier | B1: Company | C1: Website | D1: HQ / Location | E1: Founded | F1: Yrs | G1: Emp (low) | H1: Emp (high) | I1: Employee source | J1: Est. rev low ($M) | K1: Est. rev high ($M) | L1: Est. sale price low ($M) | M1: Est. sale price high ($M) | N1: 3rd-party rev est. | O1: Ownership | P1: Owner / principal | Q1: Sale signal | R1: Signal basis (inference unless noted) | S1: Clients (stated) | T1: Services focus | U1: Rating (reviews) | V1: Notes / data conflicts
A2: A | B2: ICC — Integrated Computer Consulting | C2: =HYPERLINK("https://www.iccusa.net","www.iccusa.net") -> www.iccusa.net | D2: Fort Collins | E2: 1998 | F2: =IF(E2="","",Method!$B$2-E2) -> 28 | G2: 26 | H2: 26 | I2: Verified direct count of team page | J2: =IF(G2="","",ROUND(G2*Method!$B$3/1000000,1)) -> 3.9 | K2: =IF(H2="","",ROUND(H2*Method!$B$4/1000000,1)) -> 5.2 | L2: =IF(J2="","",ROUND(J2*Method!$B$6*Method!$B$7,1)) -> 2.3 | M2: =IF(K2="","",ROUND(K2*Method!$B$6*Method!$B$8,1)) -> 5.5 | O2: Owner-operated, independent | P2: Kirk Bane (President & CEO) | Q2: High | R2: 28-yr firm, same CEO; unusually deep VP bench (3 sales VPs + VP Fin + VP Ops) suggests either professionalizing or prepping to sell | S2: 160+ clients (verified) | T2: MSP + cybersecurity; dental, mfg, healthcare, legal, accounting; 10-50 employee target clients in CO/WY | U2: 5.0 (17-23 reviews) | V2: Strongest inference-based target in Northern Colorado
A3: A | B3: InfiNet Computer Solutions | C3: =HYPERLINK("https://infinetinc.com","infinetinc.com") -> infinetinc.com | D3: Fort Collins | E3: 1998 | F3: =IF(E3="","",Method!$B$2-E3) -> 28 | G3: 8 | H3: 15 | I3: Directory <25; self-described small team | J3: =IF(G3="","",ROUND(G3*Method!$B$3/1000000,1)) -> 1.2 | K3: =IF(H3="","",ROUND(H3*Method!$B$4/1000000,1)) -> 3 | L3: =IF(J3="","",ROUND(J3*Method!$B$6*Method!$B$7,1)) -> 0.7 | M3: =IF(K3="","",ROUND(K3*Method!$B$6*Method!$B$8,1)) -> 3.2 | O3: Owner-operated | P3: Tad Osborn (President) — "same ownership since 1998" per directory language | Q3: High | R3: 28 unbroken years under one president; marketing leans on longevity/retention not growth; unmodernized service mix (web hosting, domain registration) = low reinvestment | S3: Two-decade client tenures cited | T3: MSP + cybersecurity, server admin, web hosting/design, database consulting, VPS — legacy-era service sprawl | V3: Strongest EXPLICIT succession signal found; verify headcount vs floor
A4: A | B4: Pro-IS (Professional Information Services) | C4: =HYPERLINK("https://pro-is.com","pro-is.com") -> pro-is.com | D4: Fort Collins | E4: 1998 | F4: =IF(E4="","",Method!$B$2-E4) -> 28 | G4: 10 | H4: 20 | I4: Unverified — absent from Clutch FC table; est. only | J4: =IF(G4="","",ROUND(G4*Method!$B$3/1000000,1)) -> 1.5 | K4: =IF(H4="","",ROUND(H4*Method!$B$4/1000000,1)) -> 4 | L4: =IF(J4="","",ROUND(J4*Method!$B$6*Method!$B$7,1)) -> 0.9 | M4: =IF(K4="","",ROUND(K4*Method!$B$6*Method!$B$8,1)) -> 4.2 | O4: Owner-operated | P4: Josh Orrison (Owner & CEO, Forbes Technology Council) | Q4: Moderate | R4: 28-yr firm, single named owner, notably under-documented publicly — high information-asymmetry opportunity | T4: General MSP; positions toward mid-large CO businesses | V4: Priority direct-outreach target precisely because so little is public
A5: A | B5: DCNC, Inc. | D5: Denver (N Broadway) | E5: 1998 | F5: =IF(E5="","",Method!$B$2-E5) -> 28 | G5: 13 | H5: 13 | I5: MSP Companies directory | J5: =IF(G5="","",ROUND(G5*Method!$B$3/1000000,1)) -> 2 | K5: =IF(H5="","",ROUND(H5*Method!$B$4/1000000,1)) -> 2.6 | L5: =IF(J5="","",ROUND(J5*Method!$B$6*Method!$B$7,1)) -> 1.2 | M5: =IF(K5="","",ROUND(K5*Method!$B$6*Method!$B$8,1)) -> 2.7 | O5: Owner-operated, privately held | P5: John C. Hardon (President); Derek Burnham (VP) | Q5: High | R5: 28 years, oldest independent owner-operated firm in core Denver dataset; small stable headcount, unchanged two-person leadership — textbook succession-risk profile | T5: General MSP — outsourced IT, cybersecurity, cloud, networking, software dev, backup/DR | U5: 32 reviews (Birdeye) | V5: No confirmed website domain found; verify via BBB/LinkedIn
A6: A | B6: Business Network Consulting (BNC) | C6: =HYPERLINK("https://www.bncsystems.com","www.bncsystems.com") -> www.bncsystems.com | D6: Denver | E6: 1997 | F6: =IF(E6="","",Method!$B$2-E6) -> 29 | G6: 20 | H6: 40 | I6: Clutch 10-49; DesignRush <49 — wide band | J6: =IF(G6="","",ROUND(G6*Method!$B$3/1000000,1)) -> 3 | K6: =IF(H6="","",ROUND(H6*Method!$B$4/1000000,1)) -> 8 | L6: =IF(J6="","",ROUND(J6*Method!$B$6*Method!$B$7,1)) -> 1.8 | M6: =IF(K6="","",ROUND(K6*Method!$B$6*Method!$B$8,1)) -> 8.4 | O6: Owner-operated, founder-led | P6: Joe Kelly (CEO & Founder) | Q6: High | R6: 29 years, ORIGINAL FOUNDER still sitting CEO — one of the strongest founder-tenure signals in Denver; multi-state footprint built by acquisition (TX 2007) makes it a plausible platform sale | T6: IT outsourcing, cloud/M365, cybersecurity/compliance, staff aug, 24/7 helpdesk, AI consulting; Denver/Dallas/Austin/Ft Lauderdale | U6: 5.0 (2 Clutch); 5.0 (16 DesignRush) | V6: 'Top 100 privately-held CO companies' claim unverified
A7: A | B7: GrahamGolden Technologies | C7: =HYPERLINK("https://www.grahamgoldentech.com","www.grahamgoldentech.com") -> www.grahamgoldentech.com | D7: Denver | E7: 2001 | F7: =IF(E7="","",Method!$B$2-E7) -> 25 | G7: 12 | H7: 12 | I7: RocketReach (Oct 2025), incl. offshore staff | J7: =IF(G7="","",ROUND(G7*Method!$B$3/1000000,1)) -> 1.8 | K7: =IF(H7="","",ROUND(H7*Method!$B$4/1000000,1)) -> 2.4 | L7: =IF(J7="","",ROUND(J7*Method!$B$6*Method!$B$7,1)) -> 1.1 | M7: =IF(K7="","",ROUND(K7*Method!$B$6*Method!$B$8,1)) -> 2.5 | O7: Owner-operated, two-partner | P7: Ralph Graham & Jeremy Golden (co-founding partners) | Q7: High | R7: 25 yrs, BOTH original founders still in seat; cited '35 combined years experience' at founding implies an older founder cohort now | S7: Named clients: Chipotle, SmartWool, Vail Resorts | T7: Network/server design & support, virtualization, VoIP; SMB + enterprise | V7: Offshore component may lower true rev/employee
A8: A | B8: Anchor Network Solutions | C8: =HYPERLINK("https://www.anchornetworksolutions.com","www.anchornetworksolutions.com") -> www.anchornetworksolutions.com | D8: Englewood (DTC/Inverness) | E8: 2002 | F8: =IF(E8="","",Method!$B$2-E8) -> 24 | G8: 10 | H8: 30 | I8: ~30 staff per directory sweep; company site headcount not disclosed — verify | J8: =IF(G8="","",ROUND(G8*Method!$B$3/1000000,1)) -> 1.5 | K8: =IF(H8="","",ROUND(H8*Method!$B$4/1000000,1)) -> 6 | L8: =IF(J8="","",ROUND(J8*Method!$B$6*Method!$B$7,1)) -> 0.9 | M8: =IF(K8="","",ROUND(K8*Method!$B$6*Method!$B$8,1)) -> 6.3 | O8: Owner-operated | P8: Vince Tinnirello (founder, Managing Director) | Q8: Moderate | R8: 24 yrs, founder still principal but title is 'Managing Director' not CEO, plus a LinkedIn 'Business Development' descriptor — may indicate step-back from day-to-day ops (inference from title only) | T8: IT consulting, strategic technology advisory, systems maintenance; Denver metro + NW Kansas | U8: 4.9 (77 Google) | V8: Founder active in MSP-Ignite peer-coaching group; published author/speaker
A9: A | B9: Computer Concepts Inc. (CCI) | C9: =HYPERLINK("https://www.computerci.com","www.computerci.com") -> www.computerci.com | D9: Denver | E9: 1991 | F9: =IF(E9="","",Method!$B$2-E9) -> 35 | G9: 15 | H9: 30 | I9: DesignRush band 50-99 conflicts sharply with stated footprint (20+ clients) — LOW CONFIDENCE, use with caution | J9: =IF(G9="","",ROUND(G9*Method!$B$3/1000000,1)) -> 2.3 | K9: =IF(H9="","",ROUND(H9*Method!$B$4/1000000,1)) -> 6 | L9: =IF(J9="","",ROUND(J9*Method!$B$6*Method!$B$7,1)) -> 1.4 | M9: =IF(K9="","",ROUND(K9*Method!$B$6*Method!$B$8,1)) -> 6.3 | O9: Privately held; owner not publicly named | P9: Unknown — not found anywhere in company materials | Q9: High | R9: 35 years — the longest-operating firm in the Denver dataset; owner identity itself unidentified, unusual for a firm this old; small high-value regulated client base is a strong structural succession candidate | S9: 20+ organizations, 15+ countries; 3,456 managed endpoints (verified) | T9: MSP for regulated industries — healthcare EHR/PACS, financial, insurance, legal; HIPAA/SOX/NIST/CIS compliance | V9: Headcount band unreliable — verify before using
A10: A | B10: Colorado Computer Support (CCS / CCS IT Pros) | C10: =HYPERLINK("https://coloradosupport.com","coloradosupport.com") -> coloradosupport.com | D10: Colorado Springs | E10: 2001 | F10: =IF(E10="","",Method!$B$2-E10) -> 25 | G10: 29 | H10: 29 | I10: Tracxn (Jul 2026); LinkedIn 11-50 | J10: =IF(G10="","",ROUND(G10*Method!$B$3/1000000,1)) -> 4.4 | K10: =IF(H10="","",ROUND(H10*Method!$B$4/1000000,1)) -> 5.8 | L10: =IF(J10="","",ROUND(J10*Method!$B$6*Method!$B$7,1)) -> 2.6 | M10: =IF(K10="","",ROUND(K10*Method!$B$6*Method!$B$8,1)) -> 6.1 | O10: Owner-operated, independent | P10: Blake Schwank (Founder & CEO) | Q10: High | R10: 25 yrs founder-led; SDVOSB certification is a transferable, acquisition-attractive credential | T10: Strategic IT, help desk, Apple/Mac support, virtualization; DEDICATED Defense Industrial Base practice — DFARS/NIST 800-171/CMMC readiness for Space Force/Peterson/Schriever contractors | V10: STRONGEST true-MSP defense/CMMC capability in Colorado Springs; do not confuse with 'Custom Computer Specialists' (Hauppauge NY, PE-owned, different company)
A11: A | B11: Amnet Inc. | C11: =HYPERLINK("https://www.amnet.net","www.amnet.net") -> www.amnet.net | D11: Colorado Springs (+ Denver office) | E11: 1998 | F11: =IF(E11="","",Method!$B$2-E11) -> 28 | G11: 40 | H11: 50 | I11: ZoomInfo 46, Jul 2026 — LinkedIn bands conflict 11-50 vs 51-200 | J11: =IF(G11="","",ROUND(G11*Method!$B$3/1000000,1)) -> 6 | K11: =IF(H11="","",ROUND(H11*Method!$B$4/1000000,1)) -> 10 | L11: =IF(J11="","",ROUND(J11*Method!$B$6*Method!$B$7,1)) -> 3.6 | M11: =IF(K11="","",ROUND(K11*Method!$B$6*Method!$B$8,1)) -> 10.5 | N11: ZoomInfo $89.2M is IMPLAUSIBLE (~$1.9M/employee) — disregard | O11: Owner-operated, founder-led, independent | P11: Trevor Dierdorff (Founder & CEO) | Q11: Moderate | R11: 28 yrs founder-led | T11: Managed IT, cybersecurity, cloud, backup; CJIS + HIPAA certified — local government/law-enforcement niche | U11: 4.9 (58 Google) | V11: Do not confuse with 'Amnet Systems LLC' of Stamford CT (acquired by Omega Systems/Pfingsten) — different company
A12: A | B12: TekMyBiz | C12: =HYPERLINK("https://tekmybiz.com","tekmybiz.com") -> tekmybiz.com | D12: Colorado Springs | E12: 1993 | F12: =IF(E12="","",Method!$B$2-E12) -> 33 | G12: 11 | H12: 11 | I12: ZoomInfo/LeadIQ, Jun 2025 | J12: =IF(G12="","",ROUND(G12*Method!$B$3/1000000,1)) -> 1.7 | K12: =IF(H12="","",ROUND(H12*Method!$B$4/1000000,1)) -> 2.2 | L12: =IF(J12="","",ROUND(J12*Method!$B$6*Method!$B$7,1)) -> 1 | M12: =IF(K12="","",ROUND(K12*Method!$B$6*Method!$B$8,1)) -> 2.3 | O12: Owner-operated, independent | P12: Mike Molsen (founder) | Q12: High | R12: 32+ years under the SAME NAMED FOUNDER, still personally identified with the brand — strongest age-based inference in the Colorado Springs dataset | T12: Managed IT, cybersecurity/compliance, cloud/WVD, backup, VoIP, MDM; small-business generalist | V12: Second office in Elk Grove Village IL
A13: A | B13: Springs Hosting | C13: =HYPERLINK("https://www.springshosting.com","www.springshosting.com") -> www.springshosting.com | D13: Colorado Springs | E13: 2006 | F13: =IF(E13="","",Method!$B$2-E13) -> 20 | G13: 11 | H13: 25 | I13: LinkedIn band 11-50 | J13: =IF(G13="","",ROUND(G13*Method!$B$3/1000000,1)) -> 1.7 | K13: =IF(H13="","",ROUND(H13*Method!$B$4/1000000,1)) -> 5 | L13: =IF(J13="","",ROUND(J13*Method!$B$6*Method!$B$7,1)) -> 1 | M13: =IF(K13="","",ROUND(K13*Method!$B$6*Method!$B$8,1)) -> 5.3 | N13: $11.1M (ZoomInfo/Datanyze-class est.) — plausible only if data-center revenue included | O13: Owner-operated, independent | P13: Don Brown (Founder, Owner & CEO) | Q13: Moderate | R13: 20 yrs founder-led; non-founder CIO (Jeremy Keefe) brought in ~5 yrs ago — professionalization pattern often precedes a sale | T13: Managed IT + OWNS physical data center — colocation, dedicated servers, web/email hosting, VoIP, DR; SSAE16/HIPAA/PCI/UL827 | V13: Rare asset profile: real estate + infra, not a pure MSP — different buyer calculus
A14: A | B14: Networks Unlimited, Inc. | C14: =HYPERLINK("https://networksunlimited.com","networksunlimited.com") -> networksunlimited.com | D14: Grand Junction (+ Montrose, Casper WY) | E14: 2001 | F14: =IF(E14="","",Method!$B$2-E14) -> 25 | G14: 35 | H14: 40 | I14: Company statement: grew from 2 to 35+ | J14: =IF(G14="","",ROUND(G14*Method!$B$3/1000000,1)) -> 5.3 | K14: =IF(H14="","",ROUND(H14*Method!$B$4/1000000,1)) -> 8 | L14: =IF(J14="","",ROUND(J14*Method!$B$6*Method!$B$7,1)) -> 3.2 | M14: =IF(K14="","",ROUND(K14*Method!$B$6*Method!$B$8,1)) -> 8.4 | O14: Owner-operated, independent | P14: Mark Swain (owner/founder) | Q14: Low | R14: ITSELF AN ACTIVE ACQUIRER — bought 307 Tech Pros (Casper WY) Sep 2025; behavior of a consolidator, not a seller | T14: Managed IT, cloud/productivity, cybersecurity/compliance, infrastructure, VoIP; healthcare + regional SMB verticals | V14: MSP 501, Inc. 5000, Colorado Companies to Watch — largest independent Western Slope MSP; watch as a RIVAL BUYER, not just a target
A15: A | B15: Bell Tech Pros | C15: =HYPERLINK("https://belltechpros.com","belltechpros.com") -> belltechpros.com | D15: Montrose (+ Grand Junction, Denver, Phoenix) | G15: 8 | H15: 15 | I15: Unverified — est. only | J15: =IF(G15="","",ROUND(G15*Method!$B$3/1000000,1)) -> 1.2 | K15: =IF(H15="","",ROUND(H15*Method!$B$4/1000000,1)) -> 3 | L15: =IF(J15="","",ROUND(J15*Method!$B$6*Method!$B$7,1)) -> 0.7 | M15: =IF(K15="","",ROUND(K15*Method!$B$6*Method!$B$8,1)) -> 3.2 | O15: Owner-operated, independent | P15: Joel Bell (owner) | Q15: Moderate | R15: 25+ yrs owner-operated; eponymous brand tied to owner's surname — complicates but also signals founder-identity business | S15: 1,000+ CO businesses served (cumulative marketing claim, not current MRR count) | T15: MSP, managed security/cloud, VoIP; UNUSUALLY heavy physical security/low-voltage mix — cameras, access control, building security | V15: Diversified revenue base beyond pure MSP
A16: A | B16: Mitchell and Company | C16: =HYPERLINK("https://mitchandco.com","mitchandco.com") -> mitchandco.com | D16: Carbondale + Edwards | E16: 1996 | F16: =IF(E16="","",Method!$B$2-E16) -> 30 | G16: 5 | H16: 15 | I16: Unverified — est. only | J16: =IF(G16="","",ROUND(G16*Method!$B$3/1000000,1)) -> 0.8 | K16: =IF(H16="","",ROUND(H16*Method!$B$4/1000000,1)) -> 3 | L16: =IF(J16="","",ROUND(J16*Method!$B$6*Method!$B$7,1)) -> 0.5 | M16: =IF(K16="","",ROUND(K16*Method!$B$6*Method!$B$8,1)) -> 3.2 | O16: Owner-operated, independent | P16: Not published — firm name implies founder surname Mitchell | Q16: Moderate | R16: 30 years operating, eponymous firm name, very broad but thin multi-market coverage — characteristic of a mature owner-operated lifestyle business | T16: Network technology design, implementation, unified IT infrastructure; exceptionally broad coverage: Aspen to Durango | V16: Public sector clients across Western Colorado
A17: A | B17: Decypher Technologies | C17: =HYPERLINK("https://decyphertech.com","decyphertech.com") -> decyphertech.com | D17: Glenwood Springs (+ Aspen, Vail, Denver, Palm Beach FL) | E17: 2003 | F17: =IF(E17="","",Method!$B$2-E17) -> 23 | G17: 20 | H17: 25 | I17: Directory band 'fewer than 25' | J17: =IF(G17="","",ROUND(G17*Method!$B$3/1000000,1)) -> 3 | K17: =IF(H17="","",ROUND(H17*Method!$B$4/1000000,1)) -> 5 | L17: =IF(J17="","",ROUND(J17*Method!$B$6*Method!$B$7,1)) -> 1.8 | M17: =IF(K17="","",ROUND(K17*Method!$B$6*Method!$B$8,1)) -> 5.3 | O17: Appears independent/private — no PE sponsor found | P17: Farr Shepherd (CEO); Audrey Burgio (COO); Mick Reilly (CTO) | Q17: Verify | R17: No retirement signal found — but the BEST-positioned independent asset in the resort corridor | T17: Managed IT + cybersecurity for luxury residences/family offices/hospitality; Cellular DAS & public-safety comms — genuinely differentiated UHNW niche | V17: Inc. 5000, CRN, multiple cybersecurity awards; highest-quality independent asset in mountain region
A18: A | B18: Northwest Data Services (NDS) | C18: =HYPERLINK("https://northwestdata.com","northwestdata.com") -> northwestdata.com | D18: Steamboat Springs | G18: 10 | H18: 25 | I18: ZoomInfo band 11-50 (a conflicting 100-250 figure is implausible for this market, disregard) | J18: =IF(G18="","",ROUND(G18*Method!$B$3/1000000,1)) -> 1.5 | K18: =IF(H18="","",ROUND(H18*Method!$B$4/1000000,1)) -> 5 | L18: =IF(J18="","",ROUND(J18*Method!$B$6*Method!$B$7,1)) -> 0.9 | M18: =IF(K18="","",ROUND(K18*Method!$B$6*Method!$B$8,1)) -> 5.3 | O18: Appears independent, owner-operated | P18: Jon Quinn (President) | Q18: Verify | R18: No retirement signal found — but the ONLY substantial MSP in Steamboat Springs/Routt County; effective regional incumbent with essentially no local competition | T18: Managed IT, computers/servers/networks/phones/cameras, structured wiring & fiber | V18: Scarcity value is high — white-space market
A19: B | B19: Kenyatta Computer Services (KCS) | C19: =HYPERLINK("https://kcsbus.com","kcsbus.com") -> kcsbus.com | D19: Centennial / DTC | E19: 1990 | F19: =IF(E19="","",Method!$B$2-E19) -> 36 | G19: 40 | H19: 40 | I19: CloudSecureTech company profile | J19: =IF(G19="","",ROUND(G19*Method!$B$3/1000000,1)) -> 6 | K19: =IF(H19="","",ROUND(H19*Method!$B$4/1000000,1)) -> 8 | L19: =IF(J19="","",ROUND(J19*Method!$B$6*Method!$B$7,1)) -> 3.6 | M19: =IF(K19="","",ROUND(K19*Method!$B$6*Method!$B$8,1)) -> 8.4 | O19: Owner-operated, family-held — COMPLETED generational transition | P19: Lionel Maybin (founder, 1990); Nahjee Maybin (current CEO, took over end of 2018) | Q19: Low | R19: Succession ALREADY EXECUTED (2018 handoff) — reduces near-term sale likelihood; founder retired from Air Force 2008 so likely past traditional retirement age but already stepped back | S19: 38+ companies supported across 26 states | T19: MSP, cybersecurity, 24/7 helpdesk, vCIO, structured cabling; one of few minority-owned MSPs in Denver metro | U19: 5.0 (19 verified Google) | V19: Useful comp for a completed family succession
A20: B | B20: TrinWare (Microsel of Colorado LLC) | C20: =HYPERLINK("https://trinware.com","trinware.com") -> trinware.com | D20: Centennial | E20: 2004 | F20: =IF(E20="","",Method!$B$2-E20) -> 22 | G20: 27 | H20: 28 | I20: ZoomInfo/LeadIQ, Jul 2026 | J20: =IF(G20="","",ROUND(G20*Method!$B$3/1000000,1)) -> 4.1 | K20: =IF(H20="","",ROUND(H20*Method!$B$4/1000000,1)) -> 5.6 | L20: =IF(J20="","",ROUND(J20*Method!$B$6*Method!$B$7,1)) -> 2.5 | M20: =IF(K20="","",ROUND(K20*Method!$B$6*Method!$B$8,1)) -> 5.9 | O20: Owner-operated, privately held | P20: Dan Cashman (President); David Dillion (Chief Services Officer); Kristan Anderson (CFO) | Q20: Moderate | R20: 22 yrs, stable long-tenured leadership team | T20: MSP + cybersecurity + CUSTOM HARDWARE MANUFACTURING (simulation, digital signage, esports, CAD); publishes own Denver MSP buyer's guide | V20: Hardware division complicates a clean MSP-only sale
A21: B | B21: eCreek IT Solutions | C21: =HYPERLINK("https://www.ecreekit.com","www.ecreekit.com") -> www.ecreekit.com | D21: Denver | E21: 2004 | F21: =IF(E21="","",Method!$B$2-E21) -> 22 | G21: 15 | H21: 22 | I21: Greenwood Village Chamber: '22 employees in 18 years'; a separate source cites 15 — treat as 15-22 | J21: =IF(G21="","",ROUND(G21*Method!$B$3/1000000,1)) -> 2.3 | K21: =IF(H21="","",ROUND(H21*Method!$B$4/1000000,1)) -> 4.4 | L21: =IF(J21="","",ROUND(J21*Method!$B$6*Method!$B$7,1)) -> 1.4 | M21: =IF(K21="","",ROUND(K21*Method!$B$6*Method!$B$8,1)) -> 4.6 | O21: Owner-operated / independent, self-described locally owned | P21: Scott Larson (founder, ex-Dish Network) | Q21: Moderate | R21: 22 yrs; founder had a prior full career at Dish Network before founding, implying an older founder cohort; Inc 5000 growth firms are also common sale candidates | S21: Targets orgs with 10-500 workstations | T21: Co-managed IT, cybersecurity, compliance (HIPAA/CMMC/SOC2), VoIP; Denver/Boulder/DTC/Colo Springs/Golden/Superior | U21: 4.9 (80 Google); Inc. 5000 2025 (#3,485), 3 yrs running | V21: 112% 3-yr growth per Inc. 5000
A22: A | B22: Office Automation Technologies, Inc. (OATI) | C22: =HYPERLINK("https://oati1.com","oati1.com") -> oati1.com | D22: Wheat Ridge | E22: 1994 | F22: =IF(E22="","",Method!$B$2-E22) -> 32 | G22: 10 | H22: 49 | I22: ZoomInfo band 10-49 | J22: =IF(G22="","",ROUND(G22*Method!$B$3/1000000,1)) -> 1.5 | K22: =IF(H22="","",ROUND(H22*Method!$B$4/1000000,1)) -> 9.8 | L22: =IF(J22="","",ROUND(J22*Method!$B$6*Method!$B$7,1)) -> 0.9 | M22: =IF(K22="","",ROUND(K22*Method!$B$6*Method!$B$8,1)) -> 10.3 | O22: Independent; contact listed as David Wacker (title unconfirmed as owner) | P22: David Wacker (contact; ownership unverified) | Q22: Moderate | R22: 31 yrs; no succession/next-gen leadership mentioned anywhere found — classic aging-owner profile by tenure alone | T22: Managed IT, network monitoring, cybersecurity, cloud, desktop/server support; architectural/engineering/financial verticals | U22: 5.0 (7, Chamber)
A23: A | B23: North Star, Inc. | C23: =HYPERLINK("https://www.nssit.com","www.nssit.com") -> www.nssit.com | D23: Denver | E23: 1992 | F23: =IF(E23="","",Method!$B$2-E23) -> 34 | G23: 5 | H23: 15 | I23: One aggregator says 5 (likely understated for a 30+ yr firm) — verify | J23: =IF(G23="","",ROUND(G23*Method!$B$3/1000000,1)) -> 0.8 | K23: =IF(H23="","",ROUND(H23*Method!$B$4/1000000,1)) -> 3 | L23: =IF(J23="","",ROUND(J23*Method!$B$6*Method!$B$7,1)) -> 0.5 | M23: =IF(K23="","",ROUND(K23*Method!$B$6*Method!$B$8,1)) -> 3.2 | O23: Independent, three co-owners | P23: Darryl Kalli, Brad Miles, Tony Quijano (co-owners, 'hands-on' ownership) | Q23: Moderate | R23: 33 yrs; multi-owner structure with no stated succession plan — could signal eventual generational/exit planning need | T23: Network support, cloud management, IT support/consulting | V23: Name collisions with other 'North Star' firms on Glassdoor/Indeed complicated verification
A24: B | B24: K3 Technology | C24: =HYPERLINK("https://k3techs.com","k3techs.com") -> k3techs.com | D24: Greenwood Village (+ Dallas) | E24: 2017 | F24: =IF(E24="","",Method!$B$2-E24) -> 9 | G24: 27 | H24: 27 | I24: RocketReach/LinkedIn-derived | J24: =IF(G24="","",ROUND(G24*Method!$B$3/1000000,1)) -> 4.1 | K24: =IF(H24="","",ROUND(H24*Method!$B$4/1000000,1)) -> 5.4 | L24: =IF(J24="","",ROUND(J24*Method!$B$6*Method!$B$7,1)) -> 2.5 | M24: =IF(K24="","",ROUND(K24*Method!$B$6*Method!$B$8,1)) -> 5.7 | O24: Independent; owner/founder not confirmed (Jerry Kukuchka is CFO, not confirmed owner) | P24: Unknown | Q24: Low | R24: Young company (2017) — no retirement signal found | T24: Managed IT, cybersecurity, M365, practical AI automation for growing businesses; serves Golden/Brighton via location pages | U24: ~4.96 (23 Google — 22 five-star, 1 four-star)
A25: B | B25: Lark IT (Lark Information Technology) | C25: =HYPERLINK("https://lark-it.com","lark-it.com") -> lark-it.com | D25: Denver | E25: 2003 | F25: =IF(E25="","",Method!$B$2-E25) -> 23 | G25: 15 | H25: 25 | I25: LinkedIn/Clutch band 11-50 | J25: =IF(G25="","",ROUND(G25*Method!$B$3/1000000,1)) -> 2.3 | K25: =IF(H25="","",ROUND(H25*Method!$B$4/1000000,1)) -> 5 | L25: =IF(J25="","",ROUND(J25*Method!$B$6*Method!$B$7,1)) -> 1.4 | M25: =IF(K25="","",ROUND(K25*Method!$B$6*Method!$B$8,1)) -> 5.3 | O25: Owner-operated, founder-led | P25: Tim Hochman (founding CEO) | Q25: Moderate | R25: 23 yrs, founder still CEO | T25: MSP + DevOps/IT consulting hybrid; vCIO/vCTO services, cybersecurity, systems integration
A26: B | B26: Springs IT | C26: =HYPERLINK("https://springsit.com","springsit.com") -> springsit.com | D26: Colorado Springs | E26: 2015 | F26: =IF(E26="","",Method!$B$2-E26) -> 11 | G26: 5 | H26: 15 | I26: Unverified | J26: =IF(G26="","",ROUND(G26*Method!$B$3/1000000,1)) -> 0.8 | K26: =IF(H26="","",ROUND(H26*Method!$B$4/1000000,1)) -> 3 | L26: =IF(J26="","",ROUND(J26*Method!$B$6*Method!$B$7,1)) -> 0.5 | M26: =IF(K26="","",ROUND(K26*Method!$B$6*Method!$B$8,1)) -> 3.2 | O26: Independent — RECLASSIFIED | P26: Unknown | Q26: N/A | R26: Founded 2015 — current site presents as Microsoft/Azure consulting and custom software development, no longer positions as a managed services provider | T26: Azure & cloud, Modern Work (M365), custom software dev — NOTE: has drifted out of the MSP category | U26: 5.0 (9)
A27: B | B27: RainTech | C27: =HYPERLINK("https://rain.tech","rain.tech") -> rain.tech | D27: Colorado Springs | E27: 2001 | F27: =IF(E27="","",Method!$B$2-E27) -> 25 | G27: 10 | H27: 25 | I27: Unverified — est. only | J27: =IF(G27="","",ROUND(G27*Method!$B$3/1000000,1)) -> 1.5 | K27: =IF(H27="","",ROUND(H27*Method!$B$4/1000000,1)) -> 5 | L27: =IF(J27="","",ROUND(J27*Method!$B$6*Method!$B$7,1)) -> 0.9 | M27: =IF(K27="","",ROUND(K27*Method!$B$6*Method!$B$8,1)) -> 5.3 | O27: Appears independent; no PE found | P27: Not named on about page | Q27: Verify | R27: No signal found | T27: AI services, cybersecurity, infrastructure, cloud, compliance (claims NIST 800-171); FQHC/healthcare/construction/nonprofit/PE verticals | U27: 5.0 (7) | V27: Partial CMMC-adjacent capability (NIST 800-171) without an explicit DIB practice
A28: B | B28: Colorado Hi-Tech Solutions (CHTS) | C28: =HYPERLINK("https://coloradohitechsolutions.com","coloradohitechsolutions.com") -> coloradohitechsolutions.com | D28: Colorado Springs | E28: 1996 | F28: =IF(E28="","",Method!$B$2-E28) -> 30 | G28: 10 | H28: 49 | I28: Clutch/directory band | J28: =IF(G28="","",ROUND(G28*Method!$B$3/1000000,1)) -> 1.5 | K28: =IF(H28="","",ROUND(H28*Method!$B$4/1000000,1)) -> 9.8 | L28: =IF(J28="","",ROUND(J28*Method!$B$6*Method!$B$7,1)) -> 0.9 | M28: =IF(K28="","",ROUND(K28*Method!$B$6*Method!$B$8,1)) -> 10.3 | O28: Independent | P28: Zachary King (per directory) | Q28: Moderate | R28: Three decades serving Colorado Springs commercial sector | T28: Fully + co-managed IT, managed security, VoIP/UC, SD-WAN, low-voltage cabling; extends to Pueblo
A29: B | B29: Technical Framework | C29: =HYPERLINK("https://techframework.com","techframework.com") -> techframework.com | D29: Fort Collins (+ Greeley, Loveland) | E29: 2012 | F29: =IF(E29="","",Method!$B$2-E29) -> 14 | G29: 5 | H29: 10 | I29: Clutch band 2-9 — borderline vs. size floor | J29: =IF(G29="","",ROUND(G29*Method!$B$3/1000000,1)) -> 0.8 | K29: =IF(H29="","",ROUND(H29*Method!$B$4/1000000,1)) -> 2 | L29: =IF(J29="","",ROUND(J29*Method!$B$6*Method!$B$7,1)) -> 0.5 | M29: =IF(K29="","",ROUND(K29*Method!$B$6*Method!$B$8,1)) -> 2.1 | O29: Owner-operated | P29: Al Harris (President) & Allison Robin | Q29: Low | R29: 14 yrs, two active founders — not a retirement-window target | S29: 100+ companies (cumulative claim) | T29: MSP + strong compliance posture — HIPAA/CMMC/ITAR/NIST/PCI/SOC2; construction, real estate, CPA, veterinary, law, dental, engineering verticals | V29: FC Chamber Small Business of the Year 2019; CMMC/ITAR is a genuine differentiator
A30: B | B30: iPoint Technologies | C30: =HYPERLINK("https://ipoint-tech.com","ipoint-tech.com") -> ipoint-tech.com | D30: Fort Collins | E30: 2002 | F30: =IF(E30="","",Method!$B$2-E30) -> 24 | G30: 10 | H30: 20 | I30: Conflicting: one source 10, another 20 | J30: =IF(G30="","",ROUND(G30*Method!$B$3/1000000,1)) -> 1.5 | K30: =IF(H30="","",ROUND(H30*Method!$B$4/1000000,1)) -> 4 | L30: =IF(J30="","",ROUND(J30*Method!$B$6*Method!$B$7,1)) -> 0.9 | M30: =IF(K30="","",ROUND(K30*Method!$B$6*Method!$B$8,1)) -> 4.2 | N30: $2M (reported alongside 20-emp figure) — LOW RELIABILITY | O30: Owner-operated | P30: William Bleich (President) | Q30: Moderate | R30: 24 yrs, single named president — but hybrid IT/web/marketing model makes it a messier acquisition (buying recurring MSP revenue means buying a project-services agency too) | T30: HYBRID — managed IT + website design/management + digital marketing
A31: B | B31: Crown Point Solutions | C31: =HYPERLINK("https://crownpointsolutions.com","crownpointsolutions.com") -> crownpointsolutions.com | D31: Fort Collins (+ Minneapolis-St Paul MN) | E31: 2003 | F31: =IF(E31="","",Method!$B$2-E31) -> 23 | G31: 5 | H31: 15 | I31: Unverified | J31: =IF(G31="","",ROUND(G31*Method!$B$3/1000000,1)) -> 0.8 | K31: =IF(H31="","",ROUND(H31*Method!$B$4/1000000,1)) -> 3 | L31: =IF(J31="","",ROUND(J31*Method!$B$6*Method!$B$7,1)) -> 0.5 | M31: =IF(K31="","",ROUND(K31*Method!$B$6*Method!$B$8,1)) -> 3.2 | O31: Not verified — no PE evidence found | P31: Not located | Q31: Verify | R31: 23 yrs; two-metro CO/MN split is unusual for a firm this size and may indicate an owner relocation — worth a call, insufficient public data | T31: Website design, managed IT, cybersecurity for SMB — hybrid web+IT model
A32: B | B32: Connecting Point (of Greeley) | C32: =HYPERLINK("https://www.cpcolorado.com","www.cpcolorado.com") -> www.cpcolorado.com | D32: Greeley | E32: 1985 | F32: =IF(E32="","",Method!$B$2-E32) -> 41 | G32: 17 | H32: 30 | I32: Verified direct count 17 (team page); RocketReach 26; ZoomInfo 35 | J32: =IF(G32="","",ROUND(G32*Method!$B$3/1000000,1)) -> 2.6 | K32: =IF(H32="","",ROUND(H32*Method!$B$4/1000000,1)) -> 6 | L32: =IF(J32="","",ROUND(J32*Method!$B$6*Method!$B$7,1)) -> 1.6 | M32: =IF(K32="","",ROUND(K32*Method!$B$6*Method!$B$8,1)) -> 6.3 | N32: RocketReach $15M / ZoomInfo $8.5M — likely includes hardware resale, not services-only | O32: Owner-operated, second generation | P32: Ted Warner (founder) → sons Scott Warner (Pres/CEO) & Andy Warner (CFO), 50/50 since Apr 2019 | Q32: Low | R32: Succession ALREADY EXECUTED (2019) to sons then mid-30s (~early 40s now) — opposite of a retirement-window target, but a high-quality asset if the brothers ever entertain an exit | T32: General MSP + cybersecurity, cloud, M365; VAR/hardware-resale heritage; CRN MSP 500/Pioneer 250 2024, MSP 501 | U32: ~5.0 (21+ reviews) | V32: Useful comp: clean 2-owner structure, no PE, 40-yr brand
A33: B | B33: Windward Networks | C33: =HYPERLINK("https://windwardnetworks.com","windwardnetworks.com") -> windwardnetworks.com | D33: Boulder | G33: 5 | H33: 15 | I33: Unverified — est. only | J33: =IF(G33="","",ROUND(G33*Method!$B$3/1000000,1)) -> 0.8 | K33: =IF(H33="","",ROUND(H33*Method!$B$4/1000000,1)) -> 3 | L33: =IF(J33="","",ROUND(J33*Method!$B$6*Method!$B$7,1)) -> 0.5 | M33: =IF(K33="","",ROUND(K33*Method!$B$6*Method!$B$8,1)) -> 3.2 | O33: 'Locally owned and operated' — explicit anti-roll-up positioning | P33: Not publicly named | Q33: Moderate | R33: 20+ yrs; deliberate anti-PE marketing stance cuts both ways — may signal genuine independence, or may be held by an owner who would still sell privately | T33: General MSP; clients 3-100 employees
A34: C | B34: Simplified IT Solutions (simpinc) | C34: =HYPERLINK("https://simpinc.com","simpinc.com") -> simpinc.com | D34: Lafayette / Westminster | E34: 1993 | F34: =IF(E34="","",Method!$B$2-E34) -> 33 | G34: 10 | H34: 25 | I34: Manages 1,000+ endpoints; headcount not disclosed | J34: =IF(G34="","",ROUND(G34*Method!$B$3/1000000,1)) -> 1.5 | K34: =IF(H34="","",ROUND(H34*Method!$B$4/1000000,1)) -> 5 | L34: =IF(J34="","",ROUND(J34*Method!$B$6*Method!$B$7,1)) -> 0.9 | M34: =IF(K34="","",ROUND(K34*Method!$B$6*Method!$B$8,1)) -> 5.3 | O34: Independent; founder status of current CEO UNVERIFIED | P34: Ryan Rolfsmeier (CEO) — whether he is the 1993 founder is NOT established | Q34: Verify | R34: OLDEST founding date in the entire Colorado dataset (1993) IF Rolfsmeier is the original founder — key gap to close | T34: General MSP; support/maintenance, consulting, data protection; targets 10-50 user SMBs | V34: Serves Fort Collins/Greeley/Loveland/Longmont/Lafayette/Westminster via service-area pages
A35: C | B35: TruTech IT Solutions | C35: =HYPERLINK("https://www.trutechit.com","www.trutechit.com") -> www.trutechit.com | D35: Colorado Springs (+ Pueblo, Denver, Central FL) | E35: 2010 | F35: =IF(E35="","",Method!$B$2-E35) -> 16 | G35: 10 | H35: 20 | I35: Unverified | J35: =IF(G35="","",ROUND(G35*Method!$B$3/1000000,1)) -> 1.5 | K35: =IF(H35="","",ROUND(H35*Method!$B$4/1000000,1)) -> 4 | L35: =IF(J35="","",ROUND(J35*Method!$B$6*Method!$B$7,1)) -> 0.9 | M35: =IF(K35="","",ROUND(K35*Method!$B$6*Method!$B$8,1)) -> 4.2 | O35: Appears independent | P35: Not disclosed | Q35: Verify | R35: No signal found | T35: Managed IT (fixed monthly, unlimited support model), M365, cloud backup, network/email security | V35: Unusual dual-state CO/FL footprint for a firm this size
A36: C | B36: Stepping Forward Technology | C36: =HYPERLINK("https://steppingforward.tech","steppingforward.tech") -> steppingforward.tech | D36: Colorado Springs | E36: 2006 | F36: =IF(E36="","",Method!$B$2-E36) -> 20 | G36: 10 | H36: 12 | I36: Datanyze 10; RocketReach 12 | J36: =IF(G36="","",ROUND(G36*Method!$B$3/1000000,1)) -> 1.5 | K36: =IF(H36="","",ROUND(H36*Method!$B$4/1000000,1)) -> 2.4 | L36: =IF(J36="","",ROUND(J36*Method!$B$6*Method!$B$7,1)) -> 0.9 | M36: =IF(K36="","",ROUND(K36*Method!$B$6*Method!$B$8,1)) -> 2.5 | O36: Owner-operated, husband-and-wife | P36: Matthew Harvey (CEO) & Jennifer Harvey (Co-Owner) | Q36: Verify | R36: No signal found | T36: Managed IT, strategic IT consulting, cybersecurity, cloud, compliance support
A37: C | B37: CTI Corporate Technologies, Inc. | D37: Pueblo | E37: 2003 | F37: =IF(E37="","",Method!$B$2-E37) -> 23 | G37: 5 | H37: 15 | I37: Unverified | J37: =IF(G37="","",ROUND(G37*Method!$B$3/1000000,1)) -> 0.8 | K37: =IF(H37="","",ROUND(H37*Method!$B$4/1000000,1)) -> 3 | L37: =IF(J37="","",ROUND(J37*Method!$B$6*Method!$B$7,1)) -> 0.5 | M37: =IF(K37="","",ROUND(K37*Method!$B$6*Method!$B$8,1)) -> 3.2 | O37: Veteran-owned small business | P37: Not disclosed | Q37: Verify | R37: No signal found — but the ONLY genuinely Pueblo-HQ'd MSP identified in a city of ~110K, i.e. an incumbent with almost no local competition | T37: Small business IT support/consulting/sales, network hosting/shared data center, backup | U37: 90%+ positive (source unclear, low confidence) | V37: Founding year conflicts (1990 vs 2003); website did not reliably resolve — verify directly
A38: C | B38: TriOptimum Technologies | C38: =HYPERLINK("https://www.trioptech.com","www.trioptech.com") -> www.trioptech.com | D38: Montrose | G38: 3 | H38: 5 | I38: Only 2 principals named — likely at or below size floor | J38: =IF(G38="","",ROUND(G38*Method!$B$3/1000000,1)) -> 0.5 | K38: =IF(H38="","",ROUND(H38*Method!$B$4/1000000,1)) -> 1 | L38: =IF(J38="","",ROUND(J38*Method!$B$6*Method!$B$7,1)) -> 0.3 | M38: =IF(K38="","",ROUND(K38*Method!$B$6*Method!$B$8,1)) -> 1.1 | O38: Not disclosed | P38: Chris Parker & David Turner (key personnel) | Q38: Verify | R38: No signal found | T38: Managed IT — proactive monitoring, helpdesk, endpoint security, backups; strong municipal/utility client orientation for a small firm | V38: Verify headcount before outreach
A39: C | B39: Kosh Solutions | C39: =HYPERLINK("https://www.koshsolutions.com","www.koshsolutions.com") -> www.koshsolutions.com | D39: Durango branch (HQ Las Cruces, NM) | E39: 2005 | F39: =IF(E39="","",Method!$B$2-E39) -> 21 | G39: 10 | H39: 25 | I39: Unverified — multi-state firm, CO-only share unknown | J39: =IF(G39="","",ROUND(G39*Method!$B$3/1000000,1)) -> 1.5 | K39: =IF(H39="","",ROUND(H39*Method!$B$4/1000000,1)) -> 5 | L39: =IF(J39="","",ROUND(J39*Method!$B$6*Method!$B$7,1)) -> 0.9 | M39: =IF(K39="","",ROUND(K39*Method!$B$6*Method!$B$8,1)) -> 5.3 | O39: Private — no PE sponsor found | P39: Koert Council & Joshua Fristoe (cofounders); Travis Alsup (CEO since 2012, non-founder) | Q39: Verify | R39: Non-founder professional CEO installed 2012 while both cofounders remain associated — a pattern that often precedes a sale, though no stated intent found | T39: Managed IT/network, M365, hardware rental, BCDR, CMMC compliance — explicit DIB relevance given Four Corners federal footprint | V39: 2026 MSP 501 honoree; Durango is a real staffed branch, not HQ
A40: X | B40: NexusTek | C40: =HYPERLINK("https://www.nexustek.com","www.nexustek.com") -> www.nexustek.com | D40: Greenwood Village | E40: 1996 | F40: =IF(E40="","",Method!$B$2-E40) -> 30 | G40: 250 | H40: 750 | I40: Clutch band 250-999 | J40: =IF(G40="","",ROUND(G40*Method!$B$3/1000000,1)) -> 37.5 | K40: =IF(H40="","",ROUND(H40*Method!$B$4/1000000,1)) -> 150 | L40: =IF(J40="","",ROUND(J40*Method!$B$6*Method!$B$7,1)) -> 22.5 | M40: =IF(K40="","",ROUND(K40*Method!$B$6*Method!$B$8,1)) -> 157.5 | O40: ACQUIRED — ABRY Partners (with Alvarez & Marsal Capital), Dec 13 2017, from Lightview Capital; later merged with Breakthrough Technology Group | P40: PE-controlled; no founder-owner remains | Q40: N/A | R40: ABRY has held since 2017 (9 yrs) — beyond a typical 5-7yr PE hold, an exit may be due | T40: National MSP for SMB — managed cloud, cybersecurity, business continuity; Channel Futures MSP 501, 3x CRN Triple Crown | U40: 4.2 (6 Clutch) | V40: Itself an acquirer (bought ICCS & Co)
A41: X | B41: Greystone Technology | C41: =HYPERLINK("https://www.greystonetech.com","www.greystonetech.com") -> www.greystonetech.com | D41: Denver (+ Fort Collins, Boulder offices) | E41: 2001 | F41: =IF(E41="","",Method!$B$2-E41) -> 25 | G41: 100 | H41: 249 | I41: DesignRush band 100-249 | J41: =IF(G41="","",ROUND(G41*Method!$B$3/1000000,1)) -> 15 | K41: =IF(H41="","",ROUND(H41*Method!$B$4/1000000,1)) -> 49.8 | L41: =IF(J41="","",ROUND(J41*Method!$B$6*Method!$B$7,1)) -> 9 | M41: =IF(K41="","",ROUND(K41*Method!$B$6*Method!$B$8,1)) -> 52.3 | O41: ACQUIRED — New Charter Technologies (Oval Partners), Aug 21 2020; was Cypress Growth Capital portfolio 2016-2020 | P41: Peter Melby (CEO) & Jesse Armstrong (Chairman/President) — remained post-acquisition (verify current status) | Q41: N/A | R41: Already exited twice — founders took liquidity in 2016 and 2020 | T41: Managed IT, cybersecurity, project services, web/app dev, procurement | V41: Two ownership events in 10 years — clearest evidence PE is actively buying Front Range MSPs; has a Fort Collins office too
A42: X | B42: Noynim IT Solutions → Harbor IT | C42: =HYPERLINK("https://harborit.com","harborit.com") -> harborit.com | D42: Denver | E42: 2006 | F42: =IF(E42="","",Method!$B$2-E42) -> 20 | G42: 375 | H42: 375 | I42: 375+ nationwide (parent-level, not Denver-only) | J42: =IF(G42="","",ROUND(G42*Method!$B$3/1000000,1)) -> 56.3 | K42: =IF(H42="","",ROUND(H42*Method!$B$4/1000000,1)) -> 75 | L42: =IF(J42="","",ROUND(J42*Method!$B$6*Method!$B$7,1)) -> 33.8 | M42: =IF(K42="","",ROUND(K42*Method!$B$6*Method!$B$8,1)) -> 78.8 | O42: ACQUIRED — Harbor IT (Worklyn Partners), Jun 6 2023; brand fully rebranded/absorbed | P42: Original founder no longer identified post-rebrand | Q42: N/A | R42: Already exited 2023 | T42: Cyber-first MSP — critical infrastructure, healthcare/life sciences, PE, regulated professional services | V42: noynim.com 301-redirects to harborit.com
A43: X | B43: machineLOGIC → Sourcepass | C43: =HYPERLINK("https://www.sourcepass.com/managed-it-services-denver","www.sourcepass.com/managed-it-services-denver") -> www.sourcepass.com/managed-it-services-denver | D43: Englewood | E43: 2001 | F43: =IF(E43="","",Method!$B$2-E43) -> 25 | G43: 10 | H43: 30 | I43: Not disclosed pre-acquisition | J43: =IF(G43="","",ROUND(G43*Method!$B$3/1000000,1)) -> 1.5 | K43: =IF(H43="","",ROUND(H43*Method!$B$4/1000000,1)) -> 6 | L43: =IF(J43="","",ROUND(J43*Method!$B$6*Method!$B$7,1)) -> 0.9 | M43: =IF(K43="","",ROUND(K43*Method!$B$6*Method!$B$8,1)) -> 6.3 | O43: ACQUIRED — Sourcepass, May 2023, their 8th acquisition | P43: Daniel Johnson (CEO at time of acquisition) | Q43: N/A | R43: Already exited 2023 | T43: Was cloud, security, and intelligent/RPA automation for SMB/mid-market
A44: X | B44: Verticomm | C44: =HYPERLINK("https://www.verticomm.com","www.verticomm.com") -> www.verticomm.com | D44: Denver (+ Grand Junction branch) | E44: 1999 | F44: =IF(E44="","",Method!$B$2-E44) -> 27 | G44: 61 | H44: 61 | I44: MSP Companies directory; LinkedIn band 51-200 | J44: =IF(G44="","",ROUND(G44*Method!$B$3/1000000,1)) -> 9.2 | K44: =IF(H44="","",ROUND(H44*Method!$B$4/1000000,1)) -> 12.2 | L44: =IF(J44="","",ROUND(J44*Method!$B$6*Method!$B$7,1)) -> 5.5 | M44: =IF(K44="","",ROUND(K44*Method!$B$6*Method!$B$8,1)) -> 12.8 | O44: ACQUIRED — All Copy Products (trade/strategic buyer, not PE), Sep 2015 | P44: Formerly Eric Nastri (CEO) & Rich Kennedy (President) — Kennedy now President of Elevate Services Group (completed departure) | Q44: N/A | R44: Already exited 2015; original owners have moved on | T44: Managed IT, cloud, communications, security — bundled with parent's managed print/office equipment | V44: All Copy Products = largest independent office-equipment dealer in CO, acquisition-fueled growth strategy
A45: X | B45: Vertilocity | C45: =HYPERLINK("https://vertilocity.com","vertilocity.com") -> vertilocity.com | D45: Greenwood Village (origin: Pittsburgh PA / lineage to 1986) | E45: 2007 | F45: =IF(E45="","",Method!$B$2-E45) -> 19 | G45: 50 | H45: 185 | I45: Clutch band 50-249 — too wide to be actionable | J45: =IF(G45="","",ROUND(G45*Method!$B$3/1000000,1)) -> 7.5 | K45: =IF(H45="","",ROUND(H45*Method!$B$4/1000000,1)) -> 37 | L45: =IF(J45="","",ROUND(J45*Method!$B$6*Method!$B$7,1)) -> 4.5 | M45: =IF(K45="","",ROUND(K45*Method!$B$6*Method!$B$8,1)) -> 38.9 | O45: ACQUIRED — 'an HBK company' since 2021 (HBK = accounting/professional-services firm — CPA-firm-owned MSP model) | P45: Robert L. Nelson (1986 lineage); no independent owner today | Q45: N/A | R45: Already exited 2021 | T45: Managed IT, cybersecurity, ERP/business systems consulting — consulting-weighted (only ~20% pure managed services per Clutch) | V45: High rate card ($200-300/hr)
A46: X | B46: Zivaro → Trace3 Government | D46: Denver | G46: 0 | H46: 0 | I46: Not disclosed at acquisition | J46: =IF(G46="","",ROUND(G46*Method!$B$3/1000000,1)) -> 0 | K46: =IF(H46="","",ROUND(H46*Method!$B$4/1000000,1)) -> 0 | L46: =IF(J46="","",ROUND(J46*Method!$B$6*Method!$B$7,1)) -> 0 | M46: =IF(K46="","",ROUND(K46*Method!$B$6*Method!$B$8,1)) -> 0 | O46: ACQUIRED — Trace3, Dec 19 2024; forms Trace3 Government (T3G) | P46: Not captured | Q46: N/A | R46: Already exited Dec 2024 | T46: Government/public-sector integrator — software engineering, managed hybrid cloud, SIEM; arguably outside a commercial-MSP definition | V46: Sell-side advisor: Class VI Partners (Denver); terms undisclosed
A47: X | B47: ProVelocity → IronEdge Group | C47: =HYPERLINK("https://www.ironedgegroup.com/service-areas/grand-junction/","www.ironedgegroup.com/service-areas/grand-junction") -> www.ironedgegroup.com/service-areas/grand-junction | D47: Grand Junction (pre-deal) | E47: 2003 | F47: =IF(E47="","",Method!$B$2-E47) -> 23 | G47: 10 | H47: 50 | I47: Conflicting: 10 vs 51-200 | J47: =IF(G47="","",ROUND(G47*Method!$B$3/1000000,1)) -> 1.5 | K47: =IF(H47="","",ROUND(H47*Method!$B$4/1000000,1)) -> 10 | L47: =IF(J47="","",ROUND(J47*Method!$B$6*Method!$B$7,1)) -> 0.9 | M47: =IF(K47="","",ROUND(K47*Method!$B$6*Method!$B$8,1)) -> 10.5 | O47: ACQUIRED — merged with IronEdge Group (Houston) by The Riverside Company (PE), Feb 2023; combined entity then acquired LANstar LLC Jul 20 2023 | P47: Jon Labrum (pre-deal Managing Member) | Q47: N/A | R47: Already exited 2023; real local operations originated here, now PE-owned via Houston platform | T47: Managed IT, CTO services, cybersecurity, communications, cloud | V47: Markets Grand Junction as a service area covering Fruita, Palisade, Montrose, Glenwood Springs
A48: X | B48: CommWest Corp | C48: =HYPERLINK("https://commwestcorp.com","commwestcorp.com") -> commwestcorp.com | D48: Grand Junction | E48: 2002 | F48: =IF(E48="","",Method!$B$2-E48) -> 24 | G48: 10 | H48: 25 | I48: Not disclosed (team page 403) | J48: =IF(G48="","",ROUND(G48*Method!$B$3/1000000,1)) -> 1.5 | K48: =IF(H48="","",ROUND(H48*Method!$B$4/1000000,1)) -> 5 | L48: =IF(J48="","",ROUND(J48*Method!$B$6*Method!$B$7,1)) -> 0.9 | M48: =IF(K48="","",ROUND(K48*Method!$B$6*Method!$B$8,1)) -> 5.3 | O48: ACQUIRED — Nov 11 2025 by Managing Partners Anson Pierce & Martin Jensen (operate two Florida tech firms) — out-of-state operator group, culture-preserving deal | P48: Nathan Wallace (owner since 2005, sold after ~20 yrs) | Q48: N/A | R48: CLEAREST COMPLETED SUCCESSION/EXIT EVENT in the whole Colorado dataset — Wallace's two daughters' continued employment was an explicit deal condition; seller quoted wanting to see staff/customers happy 'in a few years' | T48: Managed IT support, business communications/phone systems, cybersecurity, data recovery; Grand Junction/Fruita/Clifton/Montrose/Delta/Rifle | V48: BEST COMPARABLE for how a Western Slope succession sale actually happens
A49: X | B49: Applied Tech | C49: =HYPERLINK("https://www.appliedtech.us","www.appliedtech.us") -> www.appliedtech.us | D49: Madison WI (Lafayette/Boulder CO office) | E49: 1999 | F49: =IF(E49="","",Method!$B$2-E49) -> 27 | G49: 50 | H49: 99 | I49: Clutch band 50-249 | J49: =IF(G49="","",ROUND(G49*Method!$B$3/1000000,1)) -> 7.5 | K49: =IF(H49="","",ROUND(H49*Method!$B$4/1000000,1)) -> 19.8 | L49: =IF(J49="","",ROUND(J49*Method!$B$6*Method!$B$7,1)) -> 4.5 | M49: =IF(K49="","",ROUND(K49*Method!$B$6*Method!$B$8,1)) -> 20.8 | O49: ACQUIRED — GenNx360 Capital Partners → Heartland Business Systems (HBS, acquired by GenNx360 Oct 2025) → Applied Tech (HBS's first add-on under GenNx360, ~Apr 2026); absorbed CO's Platte River Networks (early 2023) | P49: Not disclosed | Q49: N/A | R49: Already exited; multi-layer PE chain | T49: Fully + co-managed IT, regulated security services, cloud/infrastructure; SOC 2 Type 2, Microsoft Gold Partner | U49: 4.8 (10 Clutch) | V49: Deal explicitly expands HBS into 'the Rocky Mountain region'
A50: X | B50: PEI | C50: =HYPERLINK("https://pei.com","pei.com") -> pei.com | D50: Boulder | E50: 1988 | F50: =IF(E50="","",Method!$B$2-E50) -> 38 | G50: 20 | H50: 40 | I50: DesignRush band 100-249 likely firm-wide post-deal; PEI standalone unverified | J50: =IF(G50="","",ROUND(G50*Method!$B$3/1000000,1)) -> 3 | K50: =IF(H50="","",ROUND(H50*Method!$B$4/1000000,1)) -> 8 | L50: =IF(J50="","",ROUND(J50*Method!$B$6*Method!$B$7,1)) -> 1.8 | M50: =IF(K50="","",ROUND(K50*Method!$B$6*Method!$B$8,1)) -> 8.4 | O50: ACQUIRED — Dataprise (Trinity Hunt Partners), Nov 1 2023 — explicitly Dataprise's entry INTO the Colorado market | P50: Tim Krueger (PEI President/CEO) | Q50: N/A | R50: Already exited Nov 2023 | S50: ~250 clients across Colorado | T50: Unified communications, virtualization, networking, infrastructure | V50: 38-yr-old Boulder firm; award-winning consultancy pre-acquisition
A51: X | B51: Navakai | D51: Colorado Springs | E51: 2001 | F51: =IF(E51="","",Method!$B$2-E51) -> 25 | G51: 10 | H51: 30 | I51: Not disclosed | J51: =IF(G51="","",ROUND(G51*Method!$B$3/1000000,1)) -> 1.5 | K51: =IF(H51="","",ROUND(H51*Method!$B$4/1000000,1)) -> 6 | L51: =IF(J51="","",ROUND(J51*Method!$B$6*Method!$B$7,1)) -> 0.9 | M51: =IF(K51="","",ROUND(K51*Method!$B$6*Method!$B$8,1)) -> 6.3 | O51: ACQUIRED — Ntiva (PSP Capital/Pritzker family office), deal completed Oct 1 2021 | P51: Shawn Morland & Davin Neubacher (founders) | Q51: N/A | R51: Already exited 2021 | T51: Now operates as Ntiva's 'Rocky Mountain regional hub' | V51: Terms undisclosed
A52: X | B52: Optimum Networking | C52: =HYPERLINK("https://optimumnetworking.com","optimumnetworking.com") -> optimumnetworking.com | D52: Aurora | E52: 1995 | F52: =IF(E52="","",Method!$B$2-E52) -> 31 | G52: 10 | H52: 30 | I52: Not disclosed | J52: =IF(G52="","",ROUND(G52*Method!$B$3/1000000,1)) -> 1.5 | K52: =IF(H52="","",ROUND(H52*Method!$B$4/1000000,1)) -> 6 | L52: =IF(J52="","",ROUND(J52*Method!$B$6*Method!$B$7,1)) -> 0.9 | M52: =IF(K52="","",ROUND(K52*Method!$B$6*Method!$B$8,1)) -> 6.3 | O52: ACQUIRED — Meriplex (Vitruvian Partners since Jul 2022, prior Clairvest Group), announced Nov 2021 | P52: Not disclosed | Q52: N/A | R52: Already exited 2021 | T52: Network/cybersecurity, disaster recovery, server virtualization, backup | U52: 4.3 (11 Google) | V52: Meriplex's Colorado entry point/branch; Meriplex has done 13 acquisitions since 2018
A53: F | B53: TeamLogic IT — Denver | C53: =HYPERLINK("https://www.teamlogicit.com/denverco610","www.teamlogicit.com/denverco610") -> www.teamlogicit.com/denverco610 | D53: Denver | G53: 2 | H53: 9 | I53: Franchise band 2-9 per unit; ~120 per one aggregator (likely firm-wide/multi-unit) | J53: =IF(G53="","",ROUND(G53*Method!$B$3/1000000,1)) -> 0.3 | K53: =IF(H53="","",ROUND(H53*Method!$B$4/1000000,1)) -> 1.8 | L53: =IF(J53="","",ROUND(J53*Method!$B$6*Method!$B$7,1)) -> 0.2 | M53: =IF(K53="","",ROUND(K53*Method!$B$6*Method!$B$8,1)) -> 1.9 | O53: Locally owned franchise (national TeamLogic brand) | P53: Not published | Q53: Verify | R53: Franchise resale is the standard exit path | T53: Proactive/preventative/responsive IT, emergency support | V53: Entrepreneur Magazine Top 100 Fastest Growing Franchises
A54: F | B54: TeamLogic IT — Colorado Springs | C54: =HYPERLINK("https://teamlogicit.com","teamlogicit.com") -> teamlogicit.com | D54: Colorado Springs | E54: 2011 | F54: =IF(E54="","",Method!$B$2-E54) -> 15 | G54: 2 | H54: 9 | I54: Directory band 2-9 | J54: =IF(G54="","",ROUND(G54*Method!$B$3/1000000,1)) -> 0.3 | K54: =IF(H54="","",ROUND(H54*Method!$B$4/1000000,1)) -> 1.8 | L54: =IF(J54="","",ROUND(J54*Method!$B$6*Method!$B$7,1)) -> 0.2 | M54: =IF(K54="","",ROUND(K54*Method!$B$6*Method!$B$8,1)) -> 1.9 | O54: Locally owned franchise | P54: Not published | Q54: Verify | R54: Franchise resale is the standard exit path | T54: Managed IT support, proactive security | V54: Separate franchise unit from the Denver location
A55: C | B55: CoreManaged (Denver-adjacent) | C55: =HYPERLINK("https://coremanaged.com","coremanaged.com") -> coremanaged.com | D55: Denver | O55: Unverified | P55: Unknown | Q55: Verify | T55: Co-managed IT, CMMC/NIST consulting, M365/Azure
A56: C | B56: Colorado Information Technologies, Inc. | C56: =HYPERLINK("https://www.coinfotech.com","www.coinfotech.com") -> www.coinfotech.com | D56: Colorado Springs | G56: 2 | H56: 20 | I56: CONFLICTING: one source lists 2 employees, another 10-20 — may fall below size floor, verify | J56: =IF(G56="","",ROUND(G56*Method!$B$3/1000000,1)) -> 0.3 | K56: =IF(H56="","",ROUND(H56*Method!$B$4/1000000,1)) -> 4 | L56: =IF(J56="","",ROUND(J56*Method!$B$6*Method!$B$7,1)) -> 0.2 | M56: =IF(K56="","",ROUND(K56*Method!$B$6*Method!$B$8,1)) -> 4.2 | O56: Unknown | P56: Jeremy Higham (owner) | Q56: High | R56: ~30 yrs ('30 years of network solutions' claim), single named owner, minimal digital footprint — consistent with a wind-down-stage lifestyle business (inference only) | T56: Network and server support, workstation support, proactive monitoring | V56: Microsoft Certified Partner, Cisco Partner Select

Sheet Small Shops (Roll-up)
A1: Roll-up potential | B1: Company | C1: Website | D1: City | E1: Owner / principal | F1: Founded | G1: Est. staff | H1: Service mix (recurring vs break-fix) | I1: Client base | J1: Owner tenure / age signal (inference) | K1: Rationale | L1: Notes / status
A2: High | B2: Ariel IT Services (arielMIS) | C2: =HYPERLINK("https://arielitservices.com","arielitservices.com") -> arielitservices.com | D2: Louisville | E2: 2010 | F2: 2-10 (est.) | G2: RECURRING MSP model — explicitly shifted from break-fix, 'one of the first in the area'; predecessor lineage to 1996 | H2: Bob McCool (owner; bought out 1996 co-founder; merged w/ Cam Marshall's Marshall Information Service 2006) | I2: B2B and nonprofits, Denver/Boulder/Longmont area | J2: 30-year lineage (1996-2026); owner ALREADY EXECUTED one M&A move (2006 merger) — sophisticated, deal-experienced, plausible seller | K2: Oldest lineage found in Colorado; deliberate early MSP-model adopter with prior M&A experience — strongest tuck-in candidate on this tab
A3: High | B3: TekMyBiz | C3: =HYPERLINK("https://tekmybiz.com","tekmybiz.com") -> tekmybiz.com | D3: Colorado Springs | E3: 1993 | F3: ~11 (ZoomInfo) | G3: RECURRING — cybersecurity/compliance, cloud, backup, managed IT, security cameras, VoIP, staff aug | H3: Mike Molsen (CEO/founder) | I3: SMB, Colorado Springs + Elk Grove Village IL | J3: 32-year founder tenure (1993-2026) — the STRONGEST age/tenure signal found across all of Colorado | K3: Longest-tenured founder found; real recurring B2B book; strong review volume/rating; multi-state ops = real infrastructure not a solo shop | L3: 4.9 (32 Google); 5.0 (26 TrustAnalytica)
A4: High | B4: Windward Networks | C4: =HYPERLINK("https://windwardnetworks.com","windwardnetworks.com") -> windwardnetworks.com | D4: Boulder (+ Longmont) | E4: 2004 | F4: 5 (ZoomInfo) | G4: RECURRING MSP — IT security, network upgrades, virtualization, data protection; real estate/healthcare/law verticals | H4: Kelly Garrison (Partner) | I4: B2B, Boulder/Longmont, compliance-heavy verticals | J4: 22 years operating; ~$4M revenue on 5 employees is a NOTABLY HIGH revenue-per-head ratio — strong signal of high-margin recurring revenue, not commodity break-fix | K4: Right-sized headcount, long tenure, vertical specialization, unusually strong rev/headcount ratio — one of the strongest candidates found
A5: Medium-High | B5: InfiNet Computer Solutions | C5: =HYPERLINK("https://infinetinc.com","infinetinc.com") -> infinetinc.com | D5: Fort Collins | E5: 1998 | F5: Unknown — 'same ownership since 1998' | G5: RECURRING — managed IT, cybersecurity, hosting for small businesses | H5: Tad Osborn (President) | I5: B2B, Northern Colorado | J5: 28 years, SAME OWNERSHIP throughout — strong tenure signal | K5: Very long stable single-owner tenure is a strong exit-readiness signal; headcount needs direct verification
A6: Medium-High | B6: Code Blue Computing, Inc. | C6: =HYPERLINK("https://codebluecomputing.com","codebluecomputing.com") -> codebluecomputing.com | D6: Broomfield | E6: 2009 | F6: Unknown — 'under 49' band | G6: RECURRING MSP + cybersecurity for law firms, manufacturing, CPAs | H6: Jeri Morgan (President) & Bill Morgan (Co-Owner) — husband-wife, woman-owned | I6: B2B, Denver/Boulder area, named verticals (legal, mfg, accounting) | J6: 17-year firm, husband-wife ownership — plausible succession/exit candidate given family structure and multi-decade run | K6: Strong review volume (86 Google) and rating, named B2B verticals, family-owned = often correlates with exit openness | L6: A+ BBB; 86 Google; 22 Yelp — 2nd-strongest review volume in this dataset
A7: Medium-High | B7: Netirio | C7: =HYPERLINK("https://netirio.com","netirio.com") -> netirio.com | D7: Denver / Arvada | E7: 2019 | F7: 2-10 (est.) | G7: FULLY RECURRING — managed IT, cybersecurity, cloud migration, help desk, VoIP, BCDR | H7: Avery H. George (CEO) — also previously owned 'Denver Computer Techs' | I7: B2B, Denver metro | J7: Owner claims 15+ years IT experience; ALREADY an active operator/acquirer of a second brand — may be a competitor/consolidator rather than a seller | K7: Strongest review volume in the entire dataset (72 Google, 5.0) is a real positive signal, but verify seller intent before approaching — he may be building, not selling | L7: 5.0 (72 Google) — strongest review volume found
A8: Medium-High | B8: Colorado Information Technologies, Inc. | C8: =HYPERLINK("https://www.coinfotech.com","www.coinfotech.com") -> www.coinfotech.com | D8: Colorado Springs | E8: 1986 (D&B) or ~1995 (other source) — CONFLICTING | F8: 10-20 (D&B) vs. 2 (other source) — CONFLICTING, must resolve before outreach | G8: Network consulting, server/workstation support, managed IT for SMB | H8: Jeremy Higham (owner) | I8: SMB, Colorado Springs | J8: IF the 1986 date is accurate this is a ~40-YEAR firm — an even stronger age signal than TekMyBiz; needs verification given the date conflict | K8: Potentially one of the oldest, most substantial shops found — but the headcount/founding-date conflict must be resolved first
A9: Medium | B9: Firma IT Solutions and Services | C9: =HYPERLINK("http://firmaitss.com","firmaitss.com") -> firmaitss.com | D9: Colorado Springs | E9: Rodney Gullatte, Jr. (USAF veteran, CISSP/CISO/CNDA) | G9: 3-4 (conflicting) | H9: RECURRING MSP + cybersecurity | I9: B2B, Colorado Springs; veteran/minority-owned business network ties | J9: 2019 Pikes Peak Veteran Business Owner of the Year — seasoned, credentialed operator; no clear retirement-age signal | K9: Right-sized headcount, strong ratings (5.0 Angi/HomeAdvisor, A+ BBB), veteran/minority-owned story could matter for buyer diligence | L9: 5.0 (Angi, HomeAdvisor); A+ BBB
A10: Medium | B10: Aspire Technology Solutions | C10: =HYPERLINK("https://www.aspiredenver.com","www.aspiredenver.com") -> www.aspiredenver.com | D10: Wheat Ridge | E10: 2000 | F10: ~11 | G10: RECURRING MSP — network management, data protection, cybersecurity | H10: Zachary 'Zack' Heckler (Founder & President, founded as a college freshman) | I10: B2B Denver-metro; named case studies incl. Boulder Sausage | J10: 26 years running the firm since founding at ~19-20 — founder likely mid-to-late 40s now, plausible succession-stage candidate | K10: Long tenure, real named B2B references; headcount (11) is above strict 1-5 target but relevant as a small-platform candidate
A11: Medium | B11: Pro-IS | C11: =HYPERLINK("https://pro-is.com","pro-is.com") -> pro-is.com | D11: Fort Collins | E11: 1998 | F11: 2-10 | G11: RECURRING — full-service IT support, managed IT, consulting for SMB | H11: Unknown — not identified in any source | I11: B2B SMB, Fort Collins | J11: 28-year-old firm; owner identity unknown so age/tenure can't be inferred | K11: Long tenure and right-sized headcount are attractive, but identifying the principal is the necessary first step
A12: Medium | B12: Northwest Data Services, Inc. | C12: =HYPERLINK("https://northwestdata.com","northwestdata.com") -> northwestdata.com | D12: Steamboat Springs | E12: 1993 | F12: ~11 | G12: MIXED — 'personalized technology solutions for both businesses AND homes'; also structured wiring, fiber, cameras, phones | H12: Bryan Bassett, Jon Quinn (President), Clay Ogden — General Partners | I12: Both business and residential, Steamboat Springs | J12: 33-year-old firm, multi-partner structure — a partnership nearing 3 decades often signals succession planning underway | K12: Very long tenure and multi-partner ownership; residential/consumer component dilutes the pure-B2B thesis; worth outreach to gauge partner succession intent
A13: Medium | B13: Zen Technology Solutions | C13: =HYPERLINK("https://www.zentechnologysolutions.com","www.zentechnologysolutions.com") -> www.zentechnologysolutions.com | D13: Englewood / Greenwood Village | E13: 2018 | F13: 2-3 (conflicting) | G13: FULLY RECURRING — managed firewalls/servers/WiFi, endpoint protection, security assessments, email filtering, awareness training | H13: Joshua 'Josh' Stark (Founder & CEO) | I13: Small offices, Denver-area B2B | J13: 8-year-old firm; founder profile unclear on age/prior career | K13: Genuinely recurring B2B mix is attractive, but very small and young, founder appears still building not exiting
A14: Medium | B14: Comprehensive Computer Consulting (C3) | C14: =HYPERLINK("https://c3direct.net","c3direct.net") -> c3direct.net | D14: Colorado Springs | E14: 2006 | F14: 2-18 (conflicting) | G14: RECURRING — tailored IT solutions, ongoing network infrastructure support | H14: Michael Yopp | I14: B2B SMB, Colorado Springs | J14: 20-year-old firm; owner likely peak-to-late career (inference) | K14: 20-yr tenure and clear B2B positioning are attractive; headcount conflict (2 vs 18) needs resolving before sizing as tuck-in vs. small platform
A15: Medium | B15: GrahamGolden Technologies | C15: =HYPERLINK("https://www.grahamgoldentech.com","www.grahamgoldentech.com") -> www.grahamgoldentech.com | D15: Denver | E15: 2001 | F15: 11-50 (LinkedIn) — larger than target range | G15: RECURRING — server/infrastructure design, project planning, networking, virtualization, VoIP | H15: Ralph Graham & Jeremy Golden (co-founding partners) | I15: B2B Denver | J15: 25 yrs combined; '35 combined years experience' at founding implies an older founder cohort now (50s+ inference) | K15: Too large for a clean 1-5-person tuck-in — more of a small-platform acquisition; worth tracking if mandate flexes upward
A16: Medium | B16: Wavefinity, LLC | C16: =HYPERLINK("https://wavefinity.net","wavefinity.net") -> wavefinity.net | D16: Minturn (Vail Valley/Eagle/Summit/Lake counties) | E16: Nathan Malone | G16: Likely solo/very small | H16: CLEAN RECURRING B2B/MSP — network troubleshooting, cybersecurity hardening, email security, full M365 admin/migration — no consumer-repair language found | I16: Small businesses, resort-corridor geographic moat similar to Roaring Fork Help Desk | J16: 20+ years personal IT career (inference); company/entity age unconfirmed | K16: Clean recurring model, valuable mountain-resort geographic moat, but single-operator concentration risk is high
A17: Medium | B17: DCM Technology Solutions | D17: Parker (HQ originally Illinois) | E17: Leslie A. Kleyweg; Adam Kleyweg, Denis Casarotto (family-run signal) | F17: 2001 | G17: 2-8 (conflicting) | H17: Unclear — service mix not detailed in available sources; needs direct verification | I17: Unknown/not detailed | J17: 23-25 years; Kleyweg family names suggest multi-generational/family ownership — positive succession signal | K17: Long tenure and apparent family ownership are attractive but service mix and client base unverified
A18: Medium | B18: EnTech IT Solutions | C18: =HYPERLINK("https://www.entechitsolutions.com","www.entechitsolutions.com") -> www.entechitsolutions.com | D18: Littleton | E18: 2010 | F18: 2-9 | G18: RECURRING — managed IT, cybersecurity, VoIP, data backup, cloud computing, IT consulting | H18: Bryan Evege (President & Founder) | I18: Small businesses, greater Denver area | J18: 16 years running the firm; prior career as Network Engineer at an MVNO — age unknown | K18: Solid recurring model and 16-year tenure are positives, but thin review count and unverified headcount limit confidence | L18: 5.0 (1 review — thin sample)
A19: Medium | B19: Imperitiv Solutions LLC | C19: =HYPERLINK("https://imperitiv.com","imperitiv.com") -> imperitiv.com | D19: Denver (also Castle Rock) | E19: 2015 | F19: 2-9 | G19: Managed IT support, cybersecurity, CMMC compliance, cloud — leans federal-contractor-adjacent | H19: Jeff Rash (Senior Principal Consultant, Castle Rock-based) | I19: SMBs, some federal-contractor/compliance work | J19: ~20 yrs career experience (Raytheon, Cisco, Virtela background) — age unknown | K19: CMMC/compliance specialization is valuable but thin review count (9 Google) suggests a small book | L19: 5.0 (9 Google)
A20: Medium | B20: PR27:2 Managed IT Services | C20: =HYPERLINK("https://www.pr272managedit.com","www.pr272managedit.com") -> www.pr272managedit.com | D20: Loveland | E20: 2009 (as ACTS LLC) / 2022 (current entity) | F20: 2-10 | G20: RECURRING today, but ORIGIN as home-user support (residential legacy tail possible) | H20: 'Jeff' (CEO, CISSP/CISA — surname not found) | I20: B2B (current positioning), Loveland/Fort Collins | J20: '25+ years experience' claimed (unverified); murky entity history (ACTS LLC -> partnership 2022) complicates true-age assessment | K20: Legitimate B2B positioning today with a credentialed owner, but needs diligence to separate the 17-yr operating narrative from the 4-yr legal entity fact
A21: Medium | B21: Summit Net Trekker LLC | C21: =HYPERLINK("https://computerservicebreckenridge.com","computerservicebreckenridge.com") -> computerservicebreckenridge.com | D21: Breckenridge | E21: 2001 | F21: Small — no hard number | G21: MIXED — small-business IT consulting/MSP PLUS data recovery and laptop repair | H21: Daniel 'Bud' Robinson III | I21: Small businesses, Breckenridge/Summit County | J21: 25-year-old company — strong tenure signal, age unknown | K21: Long tenure is a positive, but consumer-repair mix dilutes the recurring-revenue thesis; verify % contract vs. one-off repair
A22: Medium | B22: Roaring Fork Help Desk, Inc. | C22: =HYPERLINK("https://rfhelpdesk.net","rfhelpdesk.net") -> rfhelpdesk.net | D22: Glenwood Springs | E22: 2006 (site) or 2015 (LinkedIn) — CONFLICTING | F22: 2-10 | G22: MIXED — help desk/MSP work PLUS 'computer repair and virus removal' consumer-adjacent language | H22: Matthew McBrayer (President/Founder) | I22: Aspen, Snowmass Village, Basalt, Carbondale, Glenwood Springs — affluent resort-corridor SMBs and individuals | J22: 15+ yrs IT experience (inference); also hosts a local radio tech show — community fixture | K22: Family-run, long local roots in an affluent resort market, but consumer-repair blend and founding-date conflict need resolving
A23: Medium | B23: OliveTech LLC | C23: =HYPERLINK("https://olive.tech","olive.tech") -> olive.tech | D23: Berthoud | E23: 2021 | F23: Very small — residential address | G23: Managed IT + cybersecurity for professional-services firms; also agriculture/livestock IT | H23: Todd Hebebrand (also co-owns 'Berthoud IT') | I23: B2B, Fort Collins/Loveland/Berthoud/Northern CO | J23: Prior co-owner of 'Onix IT'; career-experienced but this entity is only ~5 years old | K23: Real B2B recurring book but very young entity, and owner appears to run a parallel venture — unclear which is the primary book
A24: Low-Medium | B24: TriOptimum Technologies | C24: =HYPERLINK("https://www.trioptech.com","www.trioptech.com") -> www.trioptech.com | D24: Montrose | E24: Christopher Thomas Parker (Owner) & David Turner (Technical Director) | F24: 2020 | G24: 2-5 (est.) | H24: MSP — 'business class computer and network support', positioned as recurring managed services | I24: B2B, Western Slope | J24: 5-year-old firm; Parker is a career Army aviation officer transitioning into IT (2nd-career founder, still studying) — growth mode not exit mode | K24: Right model and geographic moat, but too young and founder profile suggests growth, not a retirement-window exit
A25: Low | B25: Ramdyne Technology LLC | C25: =HYPERLINK("https://www.ramdyne.com","www.ramdyne.com") -> www.ramdyne.com | D25: Fort Collins | E25: 2007 | F25: 1 (ZoomInfo/D&B, ~$192K rev) | G25: Managed/recurring — network security, backup/recovery, hosted Exchange, remote support, phones | H25: Phil McNeal | I25: SMB, Fort Collins/Loveland/Greeley/Windsor | J25: 19 years running the firm — age unknown | K25: Genuine recurring book but severe key-person risk at headcount 1; verify book size before pursuing
A26: Low | B26: Integrity Technologies | C26: =HYPERLINK("https://integtech.net","integtech.net") -> integtech.net | D26: Fort Collins | E26: 2016 | F26: 2-10 | G26: Strongly recurring — help desk, cybersecurity, cloud, compliance; CPA/legal/wealth-mgmt/medical verticals | H26: Unknown | I26: B2B, vertical-specialized (compliance-heavy) | J26: 10-year-old firm, owner unidentified | K26: Strong vertical MSP model but owner unidentified and company relatively young — needs direct outreach to confirm exit readiness
A27: Low | B27: MDL Consulting Inc. | C27: =HYPERLINK("https://mdlconsultinginc.net","mdlconsultinginc.net") -> mdlconsultinginc.net | D27: Silverthorne (Summit County) | E27: 2001 | F27: 8 | G27: PRIMARILY consumer/residential repair — 'family owned and operated computer repair company' | H27: Family-owned; individual name not confirmed | I27: Mountain communities (Breckenridge, Copper, Dillon, Frisco, Keystone, Silverthorne) | J27: 25-year-old firm | K27: Consumer-repair framing despite long tenure and decent headcount — likely thin or nonexistent recurring book
A28: Low | B28: Colorado Computers | C28: =HYPERLINK("https://coloradocomputers.net","coloradocomputers.net") -> coloradocomputers.net | D28: South Denver / Parker / Castle Rock / Highlands Ranch | E28: 1997 | F28: Unknown — small/near-solo | G28: EXPLICITLY consumer/residential-leaning — on-site/in-home repair, virus removal, data recovery, training | H28: Charlie Dunham (Electrical Engineer by training) | I28: Mixed SMB and consumer | J28: 29-year owner-operator — one of the longest tenures found, but service mix is consumer-repair-dominated | K28: Very long tenure (attractive signal) undercut by consumer-repair-dominated marketing — treat as low priority unless outreach reveals an unadvertised B2B book
A29: Low | B29: Simply Tech | C29: =HYPERLINK("https://www.simplytechdenver.com","www.simplytechdenver.com") -> www.simplytechdenver.com | D29: Castle Rock | E29: 2017 | F29: Unknown — very small | G29: EXPLICITLY consumer/residential repair — 'on-site and takeaway based computer and tech repair' | H29: Unknown | I29: Mixed individual/consumer and small business | J29: 9-year-old firm, owner unidentified | K29: Consumer-repair business model, too young, owner unidentified — poor tuck-in fit
A30: Low | B30: My Computer Guy LLC | C30: =HYPERLINK("https://mycoloradocomputerguy.com","mycoloradocomputerguy.com") -> mycoloradocomputerguy.com | D30: Colorado Springs | E30: 2010 | F30: Unknown — solo/very small | G30: Branding signals consumer/residential and handyman-IT positioning — hardware, low-voltage/security installs, cloud | H30: Lenny Griffin | I30: Unclear, likely mixed consumer/small business | J30: 16 years as this entity; owner claims 20+ yrs personal career | K30: 'Computer guy' consumer-facing model rather than recurring B2B managed-services book — low roll-up value despite reasonable tenure
A31: Medium | B31: SpeedWise IT Services | C31: =HYPERLINK("https://speedwise.net","speedwise.net") -> speedwise.net | D31: Northglenn | E31: 2004 | F31: 2-3 (BBB) — at or below size floor | G31: RECURRING — VoIP, managed IT, IT consulting, cybersecurity, cloud migration | H31: Eric Frickell (owner) | I31: Small businesses, Northglenn/Denver metro | J31: 22-year operating history, single small owner — classic small lifestyle-business profile | K31: Very small but 22-yr locally-owned BBB A+ history is a plausible cheap tuck-in despite marginal size | L31: BBB A+; genuine local HQ, not a satellite office
A32: Medium | B32: Waypoint Technology Solutions | C32: =HYPERLINK("https://thinkwaypoint.com","thinkwaypoint.com") -> thinkwaypoint.com | D32: Erie | E32: 2011 | F32: 5-9 (ZoomInfo) | G32: Help desk, network/server/cloud, cybersecurity, IT project consulting — appears B2B | H32: Not identified in this pass | I32: Colorado Front Range and beyond (unspecified) | J32: 14 years operating with near-ZERO review/marketing footprint (0 reviews on Facebook and Birdeye) — inference of a steady-state, low-growth lifestyle business | K32: Genuine local Erie HQ (rare in this pass — most 'Erie' results were satellite/national); thin marketing footprint is itself a soft signal worth a direct call | L32: 0 reviews found despite 14 yrs — verify this is not a wind-down
A33: Low-Medium | B33: ITGuys (mynewitguys.com) | C33: =HYPERLINK("https://mynewitguys.com","mynewitguys.com") -> mynewitguys.com | D33: Denver / Lakewood | E33: 2009 | F33: 11-50 (ZoomInfo) — may exceed tuck-in range | G33: Managed IT, on-site computer support for small businesses; notable community angle (refurbishes recycled laptops for donation) | H33: Not identified in this pass | I33: Small businesses; serves Westminster via dedicated page | J33: 17 years operating; owner unidentified | K33: Real MSP with a positive community story, but conflicting HQ claims (downtown Denver vs. Lakewood) and unidentified owner need resolving first
A34: Low-Medium | B34: Workplace IT | C34: =HYPERLINK("https://workplaceit.net","workplaceit.net") -> workplaceit.net | D34: Arvada / Denver (HQ conflicting across own sourcing) | E34: 2016 | F34: 2 (one aggregator) — very small | G34: Managed IT, cybersecurity, IT compliance (CMMC/ITAR/FISMA/FINRA), VoIP, cloud, structured cabling | H34: Jason Canon (per aggregator; unverified) | I34: Front Range Fort Collins-to-Castle Rock (claimed) | J34: Site claims '10+ years in Denver' which conflicts with a 2016 founding date — unresolved discrepancy | K34: Real compliance-forward service mix, but HQ location and founding date both internally inconsistent — verify directly before any outreach | L34: 4.7 (14 Google, per a competitor citation — secondary source)
A36: Micro tuck-in pricing (from 2025-26 market benchmarks - see Acquirers tab):
A37: Sub-$1M revenue: 3.0-5.0x SDE. Contracted-MRR micro-MSPs price toward the top of that band; consumer/break-fix books toward the bottom. Typical structure: 65-85% cash at close, 5-15% seller note (Prime+2-4%, often PIK), 5-20% earnout tied to MRR retention over 12-24 months.
A38: Colorado's micro-market is thinner than the Triangle's but shows real activity: Networks Unlimited (Grand Junction) bought 307 Tech Pros in Casper WY (Sep 2025), and it is itself a plausible buyer for Western Slope micro-books. No confirmed acquisition of a Denver-metro or Colorado Springs micro-shop (<10 staff) was found in this pass - that segment appears genuinely under-consolidated.
A39: NOTE: this tab draws on a targeted 30-shop sweep plus a separate Boulder-focused enrichment pass - check the file date/version for the latest state. Colorado has hundreds of micro IT shops statewide; this is a sample, not an exhaustive census.

Sheet Acquirers
A1: Acquirer | B1: HQ | C1: Website | D1: Type | E1: Ownership / sponsor | F1: Colorado deals (date) | G1: Wider footprint & recent deals | H1: Appetite / criteria | I1: Actively acquiring?
A2: New Charter Technologies | B2: Denver, CO — HOME MARKET | C2: =HYPERLINK("https://www.newchartertech.com","www.newchartertech.com") -> www.newchartertech.com | D2: Permanent-capital holdco / decentralized 'equity partnership' platform (operators keep equity, retain brand/autonomy) | E2: Oval Partners (small team, ~5-6 partners) | F2: Greystone Technology, Denver (Aug 21 2020) — sole confirmed CO deal; Greystone's Peter Melby is now CEO of New Charter itself | G2: 22-30+ 'OpCo' partner firms across 28+ cities NA; CRN MSP 500 Elite 150; Inc 5000 #1986 (2025); recent: CyberTrust IT Solutions (May 2026), NetSource One (MI, Jan 2026), ProTech IT Solutions (NY, Jan 2025), Orchestrate AI Labs (Feb 2025) | H2: Mature, highly profitable MSPs (~20% EBITDA margins in founding cohort); CEO Peter Melby expects an 'active first half' of 2026 | I2: YES — the home-market platform; no 2nd CO deal since Greystone (2020) despite being HQ'd here, which is itself notable
A3: Dataprise | B3: Rockville, MD | C3: =HYPERLINK("https://www.dataprise.com","www.dataprise.com") -> www.dataprise.com | D3: PE platform | E3: Trinity Hunt Partners (since Jan 2020) | F3: PEI, Boulder (Nov 1 2023) — EXPLICITLY framed as Dataprise's entry into the Colorado market | G3: ~$130M+ revenue; 10 acquisitions, most active single acquirer of 2024; CEO David Eisner | H3: Market-entry acquisitions in new metros; mid-Atlantic base expanding west | I3: YES — Boulder is a stated new-market entry, watch for CO follow-ons
A4: Ntiva | B4: McLean, VA | C4: =HYPERLINK("https://www.ntiva.com","www.ntiva.com") -> www.ntiva.com | D4: PE platform | E4: PSP Capital (Penny Pritzker family office) | F4: Navakai, Colorado Springs (Oct 1 2021) — now Ntiva's 'Rocky Mountain regional hub' | G4: 800+ professionals; The Purple Guys (Apr 2024), Site Tech Services (Sep 2025) | H4: SMB/mid-market pure-play MSPs; vertical expertise adds; uses regional hubs as expansion anchors | I4: YES — Colorado Springs is an established regional hub, a likely base for further CO deals
A5: Meriplex | B5: Houston, TX | C5: =HYPERLINK("https://meriplex.com","meriplex.com") -> meriplex.com | D5: PE platform | E5: Vitruvian Partners (majority since Jul 2022); Clairvest Group retains minority | F5: Optimum Networking, Aurora (Nov 2021) — Meriplex's Colorado branch/entry point | G5: 13 acquisitions since 2018; also acquired Reliable IT (healthcare/financial vertical) | H5: Regional MSP branches; founder/CEO David Henley continues to run the business | I5: YES
A6: Applied Tech (Heartland Business Systems chain) | B6: Madison, WI | C6: =HYPERLINK("https://www.appliedtech.us","www.appliedtech.us") -> www.appliedtech.us | D6: Multi-layer PE chain: GenNx360 Capital Partners → Heartland Business Systems → Applied Tech | E6: GenNx360 Capital Partners acquired HBS Oct 2025; Applied Tech is HBS's FIRST add-on since that deal (~Apr 2026) | F6: Absorbed Platte River Networks (Denver, MSP 501/CRN MSP 500 honoree) into its brand, early 2023; CO office in Lafayette/Boulder | G6: Deal explicitly expands HBS into 'the Rocky Mountain region' | H6: SOC 2 Type 2, Microsoft Gold Partner shops; regional footprint expansion | I6: YES — fresh PE capital (GenNx360) behind a stated Rocky Mountain push
A7: NexusTek | B7: Greenwood Village, CO | C7: =HYPERLINK("https://www.nexustek.com","www.nexustek.com") -> www.nexustek.com | D7: PE platform | E7: ABRY Partners (with Alvarez & Marsal Capital) since Dec 13 2017, from Lightview Capital | F7: HQ'd in Colorado; merged with Breakthrough Technology Group Apr 2018 (its 4th M&A deal in <4 yrs) | G7: ~356 employees, 1,000+ customers, 44 states; still ABRY-owned in 2026, no ownership change found | H7: National MSP for SMB | I7: MODERATE — 9-yr ABRY hold is beyond a typical 5-7yr window, an exit may be due (inference)
A8: Harbor IT (via Worklyn Partners) | B8: New York, NY | C8: =HYPERLINK("https://harborit.com","harborit.com") -> harborit.com | D8: Growth-capital-backed platform (brand umbrella) | E8: Worklyn Partners | F8: Noynim IT Solutions, Denver (Jun 6 2023) — acquired directly by Worklyn, folded into the Harbor IT brand umbrella | G8: Portfolio also includes Harbor Networks, Quadrant InfoSec | H8: Regulated/critical/complex environments; life sciences & critical infrastructure | I8: YES nationally; watch for further Denver-area folding into the brand
A9: Sourcepass | B9: Jericho, NY | C9: =HYPERLINK("https://www.sourcepass.com","www.sourcepass.com") -> www.sourcepass.com | D9: Funded platform ($135M+ raised) | E9: Institutional backing; sponsor not fully verified | F9: machineLOGIC, Englewood (closed May 30 2023) — explicitly framed as expansion into the 'Western US region' | G9: 500+ staff, 2,000+ clients, 13 acquisitions since 2022 | H9: Western US region a deliberate growth target, not incidental | I9: YES
A10: Integris | B10: Cranbury, NJ (was Denver-adjacent via Compudyne lineage) | C10: =HYPERLINK("https://integrisit.com","integrisit.com") -> integrisit.com | D10: PE platform | E10: OMERS Private Equity (deal announced Dec 3 2024, closed Dec 30 2024; ex-Frontenac) | F10: Boulder, CO location traces through Compudyne (MN) → 2021 four-way merger forming Integris → now OMERS-owned; office at 2941 W 19th Ave, Denver | G10: 600+ employees nationwide; TechMD + 1nteger Security (Jun 2025) — largest to date | H10: East Coast/Midwest/South + CO/MI/MN footprint | I10: YES
A11: IronEdge Group (The Riverside Company) | B11: Houston, TX | C11: =HYPERLINK("https://www.ironedgegroup.com","www.ironedgegroup.com") -> www.ironedgegroup.com | D11: PE platform | E11: The Riverside Company | F11: ProVelocity, Grand Junction (merger closed Feb 2023); combined entity then acquired LANstar LLC (AZ, Jul 20 2023) | G11: Markets Grand Junction as a service area covering Fruita, Palisade, Montrose, Glenwood Springs | H11: Regional MSP consolidation via merger-of-equals structure | I11: YES
A12: Vertilocity (HBK) | B12: Pittsburgh, PA (Denver/Greenwood Village office) | C12: =HYPERLINK("https://vertilocity.com","vertilocity.com") -> vertilocity.com | D12: Trade buyer — CPA-firm-owned MSP model, NOT PE | E12: HBK (accounting/advisory firm, Youngstown OH) | F12: Formed 2021 via HBK's acquisition of Vertical Solutions (Pittsburgh, with Denver presence); operates from Pittsburgh, Clark NJ, and Greenwood Village CO | G12: Combined est. ~$10M gross revenue at merger (dated figure) | H12: Unusual acquirer type — accounting firms buying MSPs to bundle IT with advisory services | I12: UNCERTAIN — no new deal activity found since 2021
A13: Trace3 | B13: Irvine, CA | C13: =HYPERLINK("https://trace3.com","trace3.com") -> trace3.com | D13: Strategic integrator | E13: Not disclosed (has done multiple government-vertical acquisitions) | F13: Zivaro, Denver (Dec 19 2024) — forms 'Trace3 Government' (T3G) vertical | G13: ~200-employee Zivaro is the founding building block of T3G; full integration targeted Q2 2025 | H13: Government/public-sector, critical-infrastructure MSPs | I13: YES — Denver-based Zivaro is now the anchor of an entire new vertical
A14: All Copy Products | B14: Denver, CO | C14: =HYPERLINK("","") | D14: Trade/strategic buyer (office-equipment dealer), NOT PE | E14: Independent, Denver-based | F14: Verticomm, Denver + Grand Junction branch (Sep 15 2015) | G14: Largest independent office-equipment dealer in Colorado; acquisition-fueled growth strategy | H14: Bundles managed IT with print/office equipment | I14: UNCERTAIN — no new MSP deal found since 2015, but a real local strategic buyer type to know
A15: Networks Unlimited | B15: Grand Junction, CO — LOCAL RIVAL BUYER | C15: =HYPERLINK("https://networksunlimited.com","networksunlimited.com") -> networksunlimited.com | D15: Independent strategic acquirer (no PE sponsor found) | E15: Owner-operated (Mark Swain) | F15: Acquired 307 Tech Pros, Casper WY (~Sep 2025) — its first out-of-state deal | G15: 35+ staff, MSP 501, Inc. 5000; itself the largest independent Western Slope MSP | H15: Small MSPs in adjacent/frontier markets; owner Kyle Gamroth retained as Partner Success Manager | I15: YES — treat as a RIVAL BIDDER for any Western Slope/Mountain West micro-deal, not just a target
A16: Evergreen Services Group / Lyra | B16: San Francisco, CA (Lyra: Chicago) | C16: =HYPERLINK("https://www.evergreensg.com","www.evergreensg.com") -> www.evergreensg.com | D16: Permanent-capital holdco (buy-and-hold forever, brands kept) | E16: Alpine Investors | F16: No confirmed direct CO MSP acquisition found; Cedar Solutions Group (Evergreen/Alpine-backed GOVERNMENT-services holdco, adjacent not classic MSP) is HQ'd in Denver | G16: 100+ cumulative MSP acquisitions (100th ~Jun 2025); Lyra alone did 33 in 2025, reached $1B ARR mid-2025; targeting $5B revenue by 2030 | H16: Founder exits, fastest closes in the industry (<90 days); has visible Denver ecosystem presence via Pax8 Beyond conference | I16: WATCH — highest-volume acquirer in the industry nationally, no CO MSP deal yet but Denver ties exist
A17: The 20 MSP | B17: Plano, TX | C17: =HYPERLINK("https://www.the20msp.com","www.the20msp.com") -> www.the20msp.com | D17: Founder-led co-op roll-up — NO private equity | E17: Founder-owned; bank-debt financed | F17: UNRESOLVED — could not confirm a specific Colorado member location in this research pass | G17: 180+ locations nationwide, member-owned single-support-desk model | H17: ~$1-5M 'million-dollar MSPs'; zero earnouts | I17: UNCERTAIN — flag for a direct site-crawl follow-up if relevant
A18: Thrive Networks | B18: Foxborough, MA | C18: =HYPERLINK("https://thrivenextgen.com","thrivenextgen.com") -> thrivenextgen.com | D18: PE platform | E18: Court Square Capital + Berkshire Partners | F18: None found — no Colorado presence or acquisition identified | G18: ~$400M revenue; Northeast/Mid-Atlantic, growing Mid-South & Texas focus | H18: Cyber/cloud/compliance-heavy mid-market | I18: NOT CURRENTLY ACTIVE in Colorado per this research pass
A19: Corsica Technologies | B19: Greenville, SC / Centreville, MD | C19: =HYPERLINK("https://corsicatech.com","corsicatech.com") -> corsicatech.com | D19: PE-backed | E19: Inverness Graham | F19: None found — no Colorado presence identified | G19: AccountabilIT, Scottsdale AZ (Nov 12 2025) — doubled Corsica's capacity | H19: Midwest/Southeast/Mid-Atlantic coverage | I19: NOT CURRENTLY ACTIVE in Colorado per this research pass
A20: VC3 / Logically / Coretelligent / Magna5 / TierPoint | B20: Various | C20: =HYPERLINK("","") | D20: PE platforms named by advisory reports as active MSP consolidators | E20: Nautic Partners (VC3); The Riverside Company (Logically); Norwest Equity Partners (Coretelligent); sponsor unconfirmed (Magna5, recap in progress) | F20: NONE found with a confirmed Colorado deal in this research pass | G20: Nationally active consolidators | H20: Watch list — no CO footprint verified | I20: UNCERTAIN — TierPoint flagged Denver as a market of interest per trade press, but no completed deal found
A22: VALUATION BENCHMARKS (2025-26) — from CT Acquisitions 'IT & Managed Services M&A Multiples 2026' and companion PE guide (third-party advisory reports — treat as industry-aggregated estimates, not verified transaction-specific data)
A23: EBITDA/SDE multiples by size: sub-$1M revenue 3.0-5.0x SDE | $1-3M revenue 5.0-7.0x adj. EBITDA (peak 2020-22: 5.5-7.5x) | $3-10M revenue 6.0-9.0x EBITDA (peak: 7.0-10.0x) | $10-25M revenue (platform-scale) MSP 9.0-13.0x / MSSP 11.0-15.0x | $25M+ revenue: large MSP 10.0-14.0x / MSSP 12.0-16.0x, cyber-heavy exits up to ~20x ceiling.
A24: Recurring-revenue effect is described as 'the single largest multiple-driver': each 10-point MRR increase above the Datto-reported industry median (62%) correlates with ~0.75-1.25x multiple expansion. <40% MRR = floor pricing; ~60% MRR = threshold for 'durable managed-services franchise' perception; 80%+ MRR trades near top of size-band range. 24+ month contracts add ~1x; >10% annual churn cuts 1-3x. High-MRR/low-margin can still price BELOW lower-MRR/high-margin peers.
A25: Deal structure norms: cash at close 65-85% of EV (strategic/PE buyer) or 60-80% (financial buyer); seller notes 5-15% of EV, Prime+2-4%, 3-5yr term, often PIK; earnouts 12-24 months, 5-20% of EV tied to MRR retention (90%+ retention = full payout, <80% typically zeroes it); rollover equity 10-30% of pre-close equity value, same EV as buyer, vesting uncommon.
A26: Regional pricing (Denver/Front Range/Mountain West vs. coastal metros): NO explicit regional multiple data was found in any source. One signal: the CT Acquisitions report names a tier-1-metro premium list (NYC, SF Bay, Chicago, LA, Boston, Seattle, DC) that does NOT include Denver — suggesting Denver may be implicitly treated as tier-2/non-premium by that source, but this is an INFERENCE, not a stated data point. A Denver M&A boutique (e.g. Class VI Partners, which advised the Zivaro/Trace3 deal) would have direct regional-pricing insight if precision is needed.
A28: MOST LIKELY RIVAL BIDDERS for a Colorado target, ranked by demonstrated local intent: 1) New Charter Technologies (Denver HOME MARKET, but only 1 CO deal since 2020 — notable restraint) 2) Dataprise (Boulder is a stated new-market entry) 3) Ntiva (Colorado Springs is an established regional hub) 4) Meriplex (Aurora branch) 5) Applied Tech/HBS chain (fresh GenNx360 capital, stated Rocky Mountain push). Networks Unlimited (Grand Junction) is a RIVAL BUYER for Western Slope/Mountain West micro-deals, not just a target. Rows highlighted pink have already closed a Colorado deal.

Sheet Precedent Deals
A1: Target | B1: HQ | C1: Founded | D1: Approx. size at deal | E1: Buyer / structure | F1: Buyer type | G1: Date | H1: Notes
A2: CommWest Corp | B2: Grand Junction | C2: 2002 | D2: ~10-25 employees | E2: Anson Pierce & Martin Jensen (out-of-state operator group, 2 FL tech firms) | F2: Independent operator group, culture-preserving deal | G2: Nov 11 2025 | H2: 20-yr owner Nathan Wallace sold; two daughters' continued employment was a deal condition — clearest exit comparable in the state
A3: Noynim IT Solutions | B3: Denver | C3: 2006 | D3: 375+ staff post-deal (parent-level) | E3: Worklyn Partners (growth capital) — folded into the 'Harbor IT' brand umbrella | F3: Growth-capital acquirer; brand absorbed | G3: Jun 6 2023 | H3: CORRECTED: acquired directly by Worklyn Partners, not by 'Harbor IT' as a separate acquirer; noynim.com redirects to harborit.noynim.com
A4: PEI | B4: Boulder | C4: 1988 | D4: ~250 CO clients; 20-40 employees (est.) | E4: Dataprise (Trinity Hunt Partners) | F4: PE platform — market-entry acquisition | G4: Nov 1 2023 | H4: Explicitly framed as Dataprise's entry INTO the Colorado market; President Tim Krueger quoted
A5: Navakai | B5: Colorado Springs | C5: 2001 | D5: Not disclosed | E5: Ntiva (PSP Capital / Pritzker family office) | F5: PE platform | G5: Oct 1 2021 | H5: Founders Shawn Morland & Davin Neubacher; now Ntiva's 'Rocky Mountain regional hub'
A6: Optimum Networking | B6: Aurora | C6: 1995 | D6: Not disclosed | E6: Meriplex (Vitruvian Partners) | F6: PE platform | G6: Nov 2021 | H6: Meriplex's Colorado entry point/branch; Meriplex has done 13 acquisitions since 2018
A7: 307 Tech Pros (buyer note) | B7: Casper WY target; Grand Junction buyer | C7: 1990 | D7: Small MSP | E7: Networks Unlimited (Grand Junction) — itself the buyer, no PE sponsor found | F7: Independent strategic acquirer | G7: ~Sep 2025 | H7: Networks Unlimited's first out-of-state deal; owner Kyle Gamroth stayed on; watch as a RIVAL BUYER for Western Slope/Mountain West targets
A8: machineLOGIC | B8: Englewood | C8: 2001 | D8: Not disclosed | E8: Sourcepass | F8: PE-backed national roll-up | G8: May 2023 | H8: Sourcepass's 8th acquisition
A9: ProVelocity + LANstar | B9: Grand Junction | C9: 2003 | D9: 10-50 employees (conflicting) | E9: IronEdge Group (Houston) / The Riverside Company | F9: PE platform merger | G9: Feb 2023 (ProVelocity); Jul 20 2023 (LANstar) | H9: Real local operations originated in Grand Junction, now PE-owned via Houston platform
A10: Platte River Networks | B10: Denver | D10: MSP 501 / CRN MSP 500 honoree | E10: Applied Tech (Heartland Business Systems, itself acquired by GenNx360 Capital Oct 2025) | F10: Regional strategic roll-up | G10: Early 2023 | H10: Absorbed into the Applied Tech brand; deal chain now GenNx360 -> HBS -> Applied Tech -> Platte River
A11: Vertilocity | B11: Greenwood Village (Pittsburgh PA origin; 1986 lineage) | C11: 2007 | D11: 50-185 employees (Clutch band, wide) | E11: HBK (accounting/professional-services firm) | F11: CPA-firm-owned MSP model | G11: 2021 | H11: Trade buyer, not PE — unusual acquirer type
A12: Greystone Technology | B12: Denver (+ Fort Collins, Boulder) | C12: 2001 | D12: 100-249 employees | E12: New Charter Technologies (Oval Partners) | F12: PE platform - decentralized partnership model | G12: Aug 21 2020 | H12: Second ownership event in 4 yrs — was Cypress Growth Capital 2016-2020
A13: Greystone Technology (prior deal) | B13: Denver | C13: 2001 | E13: Cypress Growth Capital | F13: Growth-equity investor | G13: 2016 | H13: Predecessor deal before New Charter
A14: NexusTek | B14: Greenwood Village | C14: 1996 | D14: 250-999 employees | E14: ABRY Partners (with Alvarez & Marsal Capital) | F14: PE platform | G14: Dec 13 2017 | H14: Exited Lightview Capital; later merged with Breakthrough Technology Group. 9-yr hold — an exit may be due
A15: Verticomm | B15: Denver (+ Grand Junction) | C15: 1999 | D15: ~61 employees | E15: All Copy Products | F15: Trade/strategic buyer (office-equipment dealer), not PE | G15: Sep 2015 | H15: Largest independent office-equipment dealer in CO; acquisition-fueled growth strategy
A16: Networks Unlimited acquires 307 Tech Pros | B16: Grand Junction buyer; Casper WY target | C16: 1990 | D16: 307 Tech Pros founded 1990, Casper WY | E16: Networks Unlimited (Grand Junction) — itself the buyer | F16: Local strategic consolidator | G16: Sep 2025 | H16: Selling owner Kyle Gamroth stayed on as Partner Success Manager; Networks Unlimited is a RIVAL BUYER for Western Slope/Mountain West deals
A17: Zivaro | B17: Denver | D17: Not disclosed | E17: Trace3 (forms Trace3 Government) | F17: Strategic integrator acquisition | G17: Dec 19 2024 | H17: Sell-side advisor Class VI Partners (Denver); terms undisclosed
A18: Mission Critical Systems | B18: Westminster | C18: 2003 | D18: 11-50 employees; ~$1.8M standalone revenue (LeadIQ est., Apr 2025) | E18: Technology Architects (Minnesota-origin firm, independent merger — not PE) | F18: Merger of two independent MSPs | G18: Apr 2024 | H18: Combined entity now serves 4,500+ end users / 150 companies across CO/MN/WI/41 states; founder Gene Smith retained a 'continuing role' post-merger — a partial-exit succession event, not a full PE sale
A20: See the 'Acquirers' tab for the full buyer landscape, sponsors, and valuation benchmarks.
A21: Market context: 466 MSP deals closed in North America in 2025 (+20-27% YoY, $4.3B+ disclosed value, PE in 69% of disclosed deals). Three Triangle exits in the 8 months to Jul 2026 - the market has flipped from dormant to hot.

Sheet Excluded & Out of Market
A1: Company | B1: Location | C1: Reason excluded
A2: NOTE: micro-shops formerly excluded for size | B2: Colorado-wide | C2: Moved to the 'Small Shops (Roll-up)' tab with full tuck-in assessments
A3: MDL Consulting, Colorado Computers, Simply Tech, My Computer Guy LLC | B3: Summit Co / South Denver / Castle Rock / Colo Springs | C3: Explicit consumer/residential repair framing in their own marketing — poor roll-up fit despite in some cases very long tenure (Colorado Computers: 29 yrs)
A4: Tailored Technology Services Inc. | B4: Irvine CA HQ; Fort Collins satellite | C4: Ranks #1 on Clutch's Fort Collins MSP page but is a California company with a CO satellite office — commonly misfiled as local, flag explicitly
A5: Springs IT | B5: Colorado Springs | C5: Founded 2015 as an MSP; current site presents as Microsoft/Azure consulting and custom software dev — reclassified out of the MSP category
A6: Colorado Hi-Tech Solutions | B6: Colorado Springs | C6: 16-24 employees (conflicting) — too large for a tuck-in thesis, would be a platform-scale acquisition; principal identities unresolved (only initials found)
A7: Compudyne, Inc. | B7: Duluth MN HQ (Boulder CO listing) | C7: Traces through 2021 merger into Integris, now OMERS-owned — not a standalone local target
A8: Aleut Information Technology, JMark Services, Intecon LLC | B8: Colorado Springs | C8: Federal/defense-contracting focus rather than commercial SMB MSP; different buyer profile
A9: Telco United, Lionhive | B9: Programmatic city pages statewide | C9: Templated SEO location pages for essentially every Colorado city — no evidence of local operations
A10: I/O Technology Partners LLC | B10: Avon | C10: Blends web design, e-commerce, and consumer PC/Apple repair with managed services — managed services appear to be one line among many, not the core model
A11: Micro Solutions, Inc. (MSI) | B11: Glenwood Springs + Rifle | C11: Retains a consumer-facing retail/break-fix outlet alongside managed services — judgment call, flagged not excluded outright; verify recurring revenue share before outreach
A12: Cherwell Software | B12: Colorado Springs | C12: ITSM software vendor (acquired by Ivanti 2021), not an MSP
... A26: Coalfire | B26: Westminster | C26: Large national cybersecurity advisory firm, not a small-MSP tuck-in profile

Sheet Method
A1: Assumptions (edit the yellow cells - revenue estimates on 'Target List' recalculate)
A2: Current year | B2: 2026
A3: Revenue per employee - low ($) | B3: 150000
A4: Revenue per employee - high ($) | B4: 200000
A5: Basis: standard MSP benchmark of ~$150-200K annual revenue per employee. Source: industry rule of thumb (Service Leadership / channel benchmarks); user-adjustable.
A6: Assumed EBITDA margin | B6: 0.15
A7: EBITDA multiple - low (x) | B7: 4
A8: EBITDA multiple - high (x) | B8: 7
A9: Sale-price basis: est. revenue x EBITDA margin x multiple. Small SMB-focused MSPs typically trade at ~4-7x adjusted EBITDA (equivalently ~0.6-1.1x revenue at a 15% margin); high recurring-revenue mix, low client concentration, and documented processes push toward the top of the range, owner-dependence toward the bottom. Micro shops (<$1M revenue) trade lower - often 0.5-1x SDE - see the small-shops tab when present.
A12: HOW TO READ THIS WORKBOOK
A13: Tier A = prime succession-window targets: owner-operated, typically 20+ years old, founder still in charge. Tier B = established or growing firms with lower near-term sale signals. Tier C = thin data - verify before outreach. F = franchise territories. X = already acquired (competitors / valuation comps).
A14: 'Sale signal' = High / Moderate / Low / Verify / N/A. Every signal is an INFERENCE from public facts (founding year, founder tenure, career start dates, leadership changes) - never a verified owner age or a stated intention to sell. Treat as a prioritization aid, not fact.
A15: 'Est. rev low/high ($M)' are FORMULAS: employee band x revenue-per-employee assumptions above. Where a third-party estimate exists (ZoomInfo, RocketReach, D&B) it is shown in its own column - those are algorithmic estimates, not filings, and several are demonstrably wrong in this dataset (Amnet's ZoomInfo $89.2M figure implies ~$1.9M/employee and is disregarded; flagged in Notes).
A16: 'Est. sale price low/high ($M)' are FORMULAS: est. revenue x assumed EBITDA margin x EBITDA multiple (assumptions above). These are screening-level figures only - a real valuation requires actual financials, recurring-revenue mix, and client concentration. The low uses rev-low x 4x, the high rev-high x 7x, so the range is deliberately wide.
A17: Employee counts come from LinkedIn-derived aggregators (ZoomInfo, LeadIQ, RocketReach, Tracxn), directory bands (Clutch, DesignRush), company sites, and press. They lag reality and conflict often in this dataset (e.g. NexusTek shown as both 250-999 and Under-49 across sources) - verify via LinkedIn and direct contact before valuation work.
A19: MARKET SNAPSHOT (Colorado, Aug 2026)
A20: Coverage spans Denver metro, Boulder/NW metro, Colorado Springs/Southern CO, Northern Colorado (Fort Collins/Greeley), and the Western Slope/mountain resort corridor - a much larger and more geographically dispersed market than a single metro.
A21: Colorado Springs carries a distinct defense/CMMC vertical (Space Force, Peterson, Schriever, Fort Carson) - Colorado Computer Support and Imprimis Inc. are the strongest verified DIB-compliance capabilities found; most Springs MSPs have no CMMC offering at all, a real gap.
A22: Denver is New Charter Technologies' HOME MARKET (Oval Partners-backed platform) - yet it has done only ONE confirmed Denver deal (Greystone, 2020) since inception. At least 10 other national/regional platforms have separately acquired Colorado MSPs since 2015 (NexusTek/ABRY, Verticomm/All Copy, Vertilocity/HBK, Zivaro/Trace3, Noynim/Worklyn, machineLOGIC/Sourcepass, PEI/Dataprise, Navakai/Ntiva, Optimum Networking/Meriplex, Platte River/Applied Tech-HBS-GenNx360) - Denver-metro consolidation is well underway.
A23: The Western Slope is consolidating FASTER than Colorado Springs relative to market size: ProVelocity (Riverside/IronEdge, 2023), CommWest (independent operator group, Nov 2025), Verticomm (All Copy, 2015), plus Networks Unlimited itself acquiring out-of-state (307 Tech Pros, 2025) - four ownership events in a much smaller market.
... A39: This workbook was assembled from parallel research passes (by region and by function - acquirers, small shops); minor cross-references between tabs (e.g. exact employee counts) may not be perfectly reconciled. Treat the Target List as the authoritative record where tabs conflict.
